g2/4_bit_or/or_4_bit.v
module or_4_bit (
    input wire a,
    input wire b,
    input wire c,
    input wire d,
    output wire s  
);

assign s = a || b || c || d;


endmodule

g2/4_bit_or/or_4_bit_tb.v
`default_nettype none
`define DUMPSTR(x) `"or_4_bit_tb.vcd`"
`timescale 100 ns / 10 ns

module or_4_bit_tb();

parameter DURATION = 10;
reg clk = 0;
always #0.5 clk = ~clk;

reg a0, b0, c0, d0;

wire s0;

or_4_bit UUT (
           .a(a0),
           .b(b0),
           .c(c0),
           .d(d0),
           .s(s0)
         );

integer i;
reg [1:0] i_b;

initial begin

  $dumpfile(`DUMPSTR(`VCD_OUTPUT));
  $dumpvars(0, or_4_bit_tb);

  for (i = 0;i<4 ; i = i+1 ) 
  begin
      $display ("Current loop # %0d", i);
      $display ("Current loop # %0b", i);
      i_b = i;
      
      #1
      a0 = i_b[0];
      #1
      b0 = i_b[0];
      #1
      c0 = i_b[0];
      #1
      d0 = i_b[0];

  end

   #(DURATION) $display("End of simulation");
  $finish;
end

endmodule

g2/4_bit_or/or_4_bit_tb.vcd
$date
	Wed Apr 24 15:03:31 2024
$end
$version
	Icarus Verilog
$end
$timescale
	1ps
$end
$scope module or_4_bit_tb $end
$var wire 1 ! s0 $end
$var parameter 32 " DURATION $end
$var reg 1 # a0 $end
$var reg 1 $ b0 $end
$var reg 1 % c0 $end
$var reg 1 & clk $end
$var reg 1 ' d0 $end
$var reg 2 ( i_b [1:0] $end
$var integer 32 ) i [31:0] $end
$scope module UUT $end
$var wire 1 # a $end
$var wire 1 $ b $end
$var wire 1 % c $end
$var wire 1 ' d $end
$var wire 1 ! s $end
$upscope $end
$upscope $end
$enddefinitions $end
$comment Show the parameter values. $end
$dumpall
b1010 "
$end
#0
$dumpvars
b0 )
b0 (
x'
0&
x%
x$
x#
x!
$end
#50000
1&
#100000
0&
0#
#150000
1&
#200000
0&
0$
#250000
1&
#300000
0&
0%
#350000
1&
#400000
0!
0&
b1 (
b1 )
0'
#450000
1&
#500000
1!
0&
1#
#550000
1&
#600000
0&
1$
#650000
1&
#700000
0&
1%
#750000
1&
#800000
0&
b10 (
b10 )
1'
#850000
1&
#900000
0&
0#
#950000
1&
#1000000
0&
0$
#1050000
1&
#1100000
0&
0%
#1150000
1&
#1200000
0!
0&
b11 (
b11 )
0'
#1250000
1&
#1300000
1!
0&
1#
#1350000
1&
#1400000
0&
1$
#1450000
1&
#1500000
0&
1%
#1550000
1&
#1600000
0&
b100 )
1'
