g3/3c/dec_bin_prio.v
module dec_bin_prio (
    input wire [0:7] i,
    output wire [0:2] o
);

assign o = i[7] ? 3'b111 : // 7
           i[6] ? 3'b110 : // 6 
           i[5] ? 3'b101 : // 5 
           i[4] ? 3'b100 : // 4 
           i[3] ? 3'b011 : // 3 
           i[2] ? 3'b010 : // 2 
           i[1] ? 3'b001 : // 1 
           3'b000 ;// 0 ;


    
endmodule

g3/3c/dec_bin_prio_tb.v
`default_nettype none
`define DUMPSTR(x) `"dec_bin_prio_tb.vcd`"
`timescale 100 ns / 10 ns

module dec_bin_prio_tb();

parameter DURATION = 10;
reg clk = 0;
always #0.5 clk = ~clk;

reg [0:7] i0;
wire [0:2] o0;

dec_bin_prio UUT (
           .i(i0),
           .o(o0)
         );


initial begin

  $dumpfile(`DUMPSTR(`VCD_OUTPUT));
  $dumpvars(0, dec_bin_prio_tb);
    i0 = 0;
  #1 i0[0] = 1;
  #1 i0[1] = 1;
  #1 i0[2] = 1;
  #1 i0[3] = 1;
  #1 i0[4] = 1;
  #1 i0[5] = 1;
  #1 i0[6] = 1;
  #1 i0[7] = 1;
    #5

   #(DURATION) $display("End of simulation");
  $finish;
end

endmodule

g3/3c/dec_bin_prio_tb.vcd
$date
	Sat Apr 27 10:10:01 2024
$end
$version
	Icarus Verilog
$end
$timescale
	1ps
$end
$scope module dec_bin_prio_tb $end
$var wire 3 ! o0 [0:2] $end
$var parameter 32 " DURATION $end
$var reg 1 # clk $end
$var reg 8 $ i0 [0:7] $end
$scope module UUT $end
$var wire 8 % i [0:7] $end
$var wire 3 & o [0:2] $end
$upscope $end
$upscope $end
$enddefinitions $end
$comment Show the parameter values. $end
$dumpall
b1010 "
$end
#0
$dumpvars
b0 &
b0 %
b0 $
0#
b0 !
$end
#50000
1#
#100000
0#
b10000000 $
b10000000 %
#150000
1#
#200000
b1 !
b1 &
0#
b11000000 $
b11000000 %
#250000
1#
#300000
b10 !
b10 &
0#
b11100000 $
b11100000 %
#350000
1#
#400000
b11 !
b11 &
0#
b11110000 $
b11110000 %
#450000
1#
#500000
b100 !
b100 &
0#
b11111000 $
b11111000 %
#550000
1#
#600000
b101 !
b101 &
0#
b11111100 $
b11111100 %
#650000
1#
#700000
b110 !
b110 &
0#
b11111110 $
b11111110 %
#750000
1#
#800000
b111 !
b111 &
0#
b11111111 $
b11111111 %
