g4/mux_8_1/mux_8_1.v
module mux_8_1(
	input wire d0,
	input wire d1,
	input wire d2,
	input wire d3,
	input wire d4,
	input wire d5,
	input wire d6,
	input wire d7,
	input wire [0:2] opt,
	output reg o0 //reg ya que se declara dentro de de un bloque procedural
);

	always @(d0 or d1 or d2 or d3 or d4 or d5 or d6 or d7 or opt)
	begin
		case(opt)
			3'b000 : o0=d0;
			3'b001 : o0=d1;
			3'b010 : o0=d2;
			3'b011 : o0=d3;
			3'b100 : o0=d4;
			3'b101 : o0=d5;
			3'b110 : o0=d6;
			3'b111 : o0=d7;
			default: o0=d0;
		endcase	
	end
endmodule

g4/sub_1_bit/sub_1_bit.v
module sub_1_bit (
    input wire A,
    input wire B,
    input wire Bin,
    output wire D,
    output wire Bout
);
    
assign D = (!A)*(!B)*Bin + (!A)*B*(!Bin) + A*(!B)*(!Bin) + A*B*Bin;
assign Bout = (!A)*(!B)*Bin + (!A)*B*(!Bin) + (!A)*B*Bin + A*B*Bin;



/* A*B+((!A)*B+A*(!B))*Cin;
 */
endmodule

g4/sum_1_bit/sum_1_bit.v
module sum_1_bit (
    input wire A,
    input wire B,
    input wire Cin,
    output wire S,
    output wire Cout
);
    
assign S = (!A)*(!B)*Cin + (!A)*B*(!Cin) + A*(!B)*(!Cin) + A*B*Cin;
assign Cout = A*B+((!A)*B+A*(!B))*Cin;
endmodule

g4/alu_1_bit.v
`include "sum_1_bit/sum_1_bit.v"    
`include "sub_1_bit/sub_1_bit.v"    
`include "mux_8_1/mux_8_1.v"    

module alu_1_bit (
    input wire A,
    input wire B,
    input wire Cin,
    input wire [0:2]Op,
    output wire O,
    output wire Z,
    output wire P,
    output wire Cout
);
    
wire suma_s, suma_c_out, resta_d, resta_b_out;
wire and_ab, or_ab, not_a;
wire tmp_o, tmp_c_out;

assign and_ab = A & B;
assign or_ab = A | B;
assign not_a = ~A;

sum_1_bit sum_1_bit_0(
    .A(A),
    .B(B),
    .Cin(Cin),
    .S(suma_s),
    .Cout(suma_c_out)
);

sub_1_bit sub_1_bit_0(
    .A(A),
    .B(B),
    .Bin(Cin),
    .D(resta_d),
    .Bout(resta_b_out)
);

mux_8_1 mux_8_1_o(
    .d0(1'b0),
    .d1(suma_s),
    .d2(resta_d),
    .d3(1'b0),
    .d4(or_ab),
    .d5(and_ab),
    .d6(not_a),
    .d7(1'b0),
    .opt(Op),
    .o0(tmp_o)

);
mux_8_1 mux_8_1_c(
    .d0(1'b0),
    .d1(suma_c_out),
    .d2(resta_b_out),
    .d3(1'b0),
    .d4(1'b0),
    .d5(1'b0),
    .d6(1'b0),
    .d7(1'b0),
    .opt(Op),
    .o0(tmp_c_out)
);

assign O = tmp_o;
assign Cout = tmp_c_out;
assign P = tmp_o ^ 1'b0;
assign Z =  ~tmp_o;


endmodule

g4/alu_1_bit_tb.v
`default_nettype none
`define DUMPSTR(x) `"alu_1_bit_tb.vcd`"
`timescale 100 ns / 10 ns

module alu_1_bit_tb();

parameter DURATION = 10;
reg clk = 0;
always #0.5 clk = ~clk;

reg  a0, b0 , ci0;
wire  o0, z0, p0;
reg [2:0] opt0;
wire co0;

alu_1_bit UUT (
    .A(a0),
    .B(b0),
    .Cin(ci0),
    .Op(opt0),
    .O(o0),
    .Z(z0),
    .P(p0),
    .Cout(co0)
           
         );

integer i, j;
reg [2:0] i_b;

initial begin

  $dumpfile(`DUMPSTR(`VCD_OUTPUT));
  $dumpvars(0, alu_1_bit_tb);
  for (i = 0;i<8 ;i=i+1)
  	begin
  	    for(j=0;j<8;j=j+1)
            begin
                #2;
                i_b = i;
                a0 = i_b[2];
                b0 = i_b[1];
                ci0 = i_b[0];
                opt0 = j;
                
            end	
  end


    #(DURATION) $display("End of simulation");
   $finish;
end

endmodule

g4/alu_1_bit_tb.vcd
$date
	Fri May 24 19:43:47 2024
$end
$version
	Icarus Verilog
$end
$timescale
	1ps
$end
$scope module alu_1_bit_tb $end
$var wire 1 ! z0 $end
$var wire 1 " p0 $end
$var wire 1 # o0 $end
$var wire 1 $ co0 $end
$var parameter 32 % DURATION $end
$var reg 1 & a0 $end
$var reg 1 ' b0 $end
$var reg 1 ( ci0 $end
$var reg 1 ) clk $end
$var reg 3 * i_b [2:0] $end
$var reg 3 + opt0 [2:0] $end
$var integer 32 , i [31:0] $end
$var integer 32 - j [31:0] $end
$scope module UUT $end
$var wire 1 & A $end
$var wire 1 ' B $end
$var wire 1 ( Cin $end
$var wire 1 $ Cout $end
$var wire 1 # O $end
$var wire 3 . Op [0:2] $end
$var wire 1 " P $end
$var wire 1 ! Z $end
$var wire 1 / and_ab $end
$var wire 1 0 not_a $end
$var wire 1 1 or_ab $end
$var wire 1 2 tmp_o $end
$var wire 1 3 tmp_c_out $end
$var wire 1 4 suma_s $end
$var wire 1 5 suma_c_out $end
$var wire 1 6 resta_d $end
$var wire 1 7 resta_b_out $end
$scope module mux_8_1_c $end
$var wire 1 8 d0 $end
$var wire 1 9 d3 $end
$var wire 1 : d4 $end
$var wire 1 ; d5 $end
$var wire 1 < d6 $end
$var wire 1 = d7 $end
$var wire 3 > opt [0:2] $end
$var wire 1 7 d2 $end
$var wire 1 5 d1 $end
$var reg 1 3 o0 $end
$upscope $end
$scope module mux_8_1_o $end
$var wire 1 ? d0 $end
$var wire 1 @ d3 $end
$var wire 1 1 d4 $end
$var wire 1 / d5 $end
$var wire 1 0 d6 $end
$var wire 1 A d7 $end
$var wire 3 B opt [0:2] $end
$var wire 1 6 d2 $end
$var wire 1 4 d1 $end
$var reg 1 2 o0 $end
$upscope $end
$scope module sub_1_bit_0 $end
$var wire 1 & A $end
$var wire 1 ' B $end
$var wire 1 ( Bin $end
$var wire 1 6 D $end
$var wire 1 7 Bout $end
$upscope $end
$scope module sum_1_bit_0 $end
$var wire 1 & A $end
$var wire 1 ' B $end
$var wire 1 ( Cin $end
$var wire 1 4 S $end
$var wire 1 5 Cout $end
$upscope $end
$upscope $end
$upscope $end
$enddefinitions $end
$comment Show the parameter values. $end
$dumpall
b1010 %
$end
#0
$dumpvars
bx B
0A
0@
0?
bx >
0=
0<
0;
0:
09
08
x7
x6
x5
x4
03
02
x1
x0
x/
bx .
b0 -
b0 ,
bx +
bx *
0)
x(
x'
x&
0$
0#
0"
1!
$end
#50000
1)
#100000
0)
#150000
1)
#200000
0/
01
10
0)
b1 -
b0 +
b0 .
b0 >
b0 B
06
07
04
05
0(
0'
0&
b0 *
#250000
1)
#300000
0)
#350000
1)
#400000
0)
b10 -
b1 +
b1 .
b1 >
b1 B
#450000
1)
#500000
0)
#550000
1)
#600000
0)
b11 -
b10 +
b10 .
b10 >
b10 B
#650000
1)
#700000
0)
#750000
1)
#800000
0)
b100 -
b11 +
b11 .
b11 >
b11 B
#850000
1)
#900000
0)
#950000
1)
#1000000
0)
b101 -
b100 +
b100 .
b100 >
b100 B
#1050000
1)
#1100000
0)
#1150000
1)
#1200000
0)
b110 -
b101 +
b101 .
b101 >
b101 B
#1250000
1)
#1300000
0)
#1350000
1)
#1400000
0!
1"
1#
12
0)
b111 -
b110 +
b110 .
b110 >
b110 B
#1450000
1)
#1500000
0)
#1550000
1)
#1600000
1!
0"
0#
02
0)
b1 ,
b0 -
b111 +
b111 .
b111 >
b111 B
#1650000
1)
#1700000
0)
#1750000
1)
#1800000
0)
b1 -
b0 +
b0 .
b0 >
b0 B
16
17
14
1(
b1 *
#1850000
1)
#1900000
0)
#1950000
1)
#2000000
0!
1"
1#
12
0)
b10 -
b1 +
b1 .
b1 >
b1 B
#2050000
1)
#2100000
0)
#2150000
1)
#2200000
1$
13
0)
b11 -
b10 +
b10 .
b10 >
b10 B
#2250000
1)
#2300000
0)
#2350000
1)
#2400000
1!
0"
0$
03
0#
02
0)
b100 -
b11 +
b11 .
b11 >
b11 B
#2450000
1)
#2500000
0)
#2550000
1)
#2600000
0)
b101 -
b100 +
b100 .
b100 >
b100 B
#2650000
1)
#2700000
0)
#2750000
1)
#2800000
0)
b110 -
b101 +
b101 .
b101 >
b101 B
#2850000
1)
#2900000
0)
#2950000
1)
#3000000
0!
1"
1#
12
0)
b111 -
b110 +
b110 .
b110 >
b110 B
#3050000
1)
#3100000
0)
#3150000
1)
#3200000
1!
0"
0#
02
0)
b10 ,
b0 -
b111 +
b111 .
b111 >
b111 B
#3250000
1)
#3300000
0)
#3350000
1)
#3400000
11
0)
b1 -
b0 +
b0 .
b0 >
b0 B
0(
16
17
14
05
1'
b10 *
#3450000
1)
#3500000
0)
#3550000
1)
#3600000
0!
1"
1#
12
0)
b10 -
b1 +
b1 .
b1 >
b1 B
#3650000
1)
#3700000
0)
#3750000
1)
#3800000
1$
13
0)
b11 -
b10 +
b10 .
b10 >
b10 B
#3850000
1)
#3900000
0)
#3950000
1)
#4000000
1!
0"
0$
03
0#
02
0)
b100 -
b11 +
b11 .
b11 >
b11 B
#4050000
1)
#4100000
0)
#4150000
1)
#4200000
0!
1"
1#
12
0)
b101 -
b100 +
b100 .
b100 >
b100 B
#4250000
1)
#4300000
0)
#4350000
1)
#4400000
1!
0"
0#
02
0)
b110 -
b101 +
b101 .
b101 >
b101 B
#4450000
1)
#4500000
0)
#4550000
1)
#4600000
0!
1"
1#
12
0)
b111 -
b110 +
b110 .
b110 >
b110 B
#4650000
1)
#4700000
0)
#4750000
1)
#4800000
1!
0"
0#
02
0)
b11 ,
b0 -
b111 +
b111 .
b111 >
b111 B
#4850000
1)
#4900000
0)
#4950000
1)
#5000000
0)
b1 -
b0 +
b0 .
b0 >
b0 B
06
17
04
15
1(
b11 *
#5050000
1)
#5100000
0)
#5150000
1)
#5200000
1$
13
0)
b10 -
b1 +
b1 .
b1 >
b1 B
#5250000
1)
#5300000
0)
#5350000
1)
#5400000
0)
b11 -
b10 +
b10 .
b10 >
b10 B
#5450000
1)
#5500000
0)
#5550000
1)
#5600000
0$
03
0)
b100 -
b11 +
b11 .
b11 >
b11 B
#5650000
1)
#5700000
0)
#5750000
1)
#5800000
0!
1"
1#
12
0)
b101 -
b100 +
b100 .
b100 >
b100 B
#5850000
1)
#5900000
0)
#5950000
1)
#6000000
1!
0"
0#
02
0)
b110 -
b101 +
b101 .
b101 >
b101 B
#6050000
1)
#6100000
0)
#6150000
1)
#6200000
0!
1"
1#
12
0)
b111 -
b110 +
b110 .
b110 >
b110 B
#6250000
1)
#6300000
0)
#6350000
1)
#6400000
1!
0"
0#
02
0)
b100 ,
b0 -
b111 +
b111 .
b111 >
b111 B
#6450000
1)
#6500000
0)
#6550000
1)
#6600000
00
0)
b1 -
b0 +
b0 .
b0 >
b0 B
0(
0'
16
07
14
05
1&
b100 *
#6650000
1)
#6700000
0)
#6750000
1)
#6800000
0!
1"
1#
12
0)
b10 -
b1 +
b1 .
b1 >
b1 B
#6850000
1)
#6900000
0)
#6950000
1)
#7000000
0)
b11 -
b10 +
b10 .
b10 >
b10 B
#7050000
1)
#7100000
0)
#7150000
1)
#7200000
1!
0"
0#
02
0)
b100 -
b11 +
b11 .
b11 >
b11 B
#7250000
1)
#7300000
0)
#7350000
1)
#7400000
0!
1"
1#
12
0)
b101 -
b100 +
b100 .
b100 >
b100 B
#7450000
1)
#7500000
0)
#7550000
1)
#7600000
1!
0"
0#
02
0)
b110 -
b101 +
b101 .
b101 >
b101 B
#7650000
1)
#7700000
0)
#7750000
1)
#7800000
0)
b111 -
b110 +
b110 .
b110 >
b110 B
#7850000
1)
#7900000
0)
#7950000
1)
#8000000
0)
b101 ,
b0 -
b111 +
b111 .
b111 >
b111 B
#8050000
1)
#8100000
0)
#8150000
1)
#8200000
0)
b1 -
b0 +
b0 .
b0 >
b0 B
06
04
15
1(
b101 *
#8250000
1)
#8300000
0)
#8350000
1)
#8400000
1$
13
0)
b10 -
b1 +
b1 .
b1 >
b1 B
#8450000
1)
#8500000
0)
#8550000
1)
#8600000
0$
03
0)
b11 -
b10 +
b10 .
b10 >
b10 B
#8650000
1)
#8700000
0)
#8750000
1)
#8800000
0)
b100 -
b11 +
b11 .
b11 >
b11 B
#8850000
1)
#8900000
0)
#8950000
1)
#9000000
0!
1"
1#
12
0)
b101 -
b100 +
b100 .
b100 >
b100 B
#9050000
1)
#9100000
0)
#9150000
1)
#9200000
1!
0"
0#
02
0)
b110 -
b101 +
b101 .
b101 >
b101 B
#9250000
1)
#9300000
0)
#9350000
1)
#9400000
0)
b111 -
b110 +
b110 .
b110 >
b110 B
#9450000
1)
#9500000
0)
#9550000
1)
#9600000
0)
b110 ,
b0 -
b111 +
b111 .
b111 >
b111 B
#9650000
1)
#9700000
0)
#9750000
1)
#9800000
1/
0)
b1 -
b0 +
b0 .
b0 >
b0 B
0(
06
07
04
15
1'
b110 *
#9850000
1)
#9900000
0)
#9950000
1)
#10000000
1$
13
0)
b10 -
b1 +
b1 .
b1 >
b1 B
#10050000
1)
#10100000
0)
#10150000
1)
#10200000
0$
03
0)
b11 -
b10 +
b10 .
b10 >
b10 B
#10250000
1)
#10300000
0)
#10350000
1)
#10400000
0)
b100 -
b11 +
b11 .
b11 >
b11 B
#10450000
1)
#10500000
0)
#10550000
1)
#10600000
0!
1"
1#
12
0)
b101 -
b100 +
b100 .
b100 >
b100 B
#10650000
1)
#10700000
0)
#10750000
1)
#10800000
0)
b110 -
b101 +
b101 .
b101 >
b101 B
#10850000
1)
#10900000
0)
#10950000
1)
#11000000
1!
0"
0#
02
0)
b111 -
b110 +
b110 .
b110 >
b110 B
#11050000
1)
#11100000
0)
#11150000
1)
#11200000
0)
b111 ,
b0 -
b111 +
b111 .
b111 >
b111 B
#11250000
1)
#11300000
0)
#11350000
1)
#11400000
0)
b1 -
b0 +
b0 .
b0 >
b0 B
16
17
14
1(
b111 *
#11450000
1)
#11500000
0)
#11550000
1)
#11600000
0!
1"
1$
13
1#
12
0)
b10 -
b1 +
b1 .
b1 >
b1 B
#11650000
1)
#11700000
0)
#11750000
1)
#11800000
0)
b11 -
b10 +
b10 .
b10 >
b10 B
#11850000
1)
#11900000
0)
#11950000
1)
#12000000
1!
0"
0$
03
0#
02
0)
b100 -
b11 +
b11 .
b11 >
b11 B
#12050000
1)
#12100000
0)
#12150000
1)
#12200000
0!
1"
1#
12
0)
b101 -
b100 +
b100 .
b100 >
b100 B
#12250000
1)
#12300000
0)
#12350000
1)
#12400000
0)
b110 -
b101 +
b101 .
b101 >
b101 B
#12450000
1)
#12500000
0)
#12550000
1)
#12600000
1!
0"
0#
02
0)
b111 -
b110 +
b110 .
b110 >
b110 B
#12650000
1)
#12700000
0)
#12750000
1)
#12800000
0)
b1000 ,
b1000 -
b111 +
b111 .
b111 >
b111 B
