g6/ej1/D/DFF.v
module DFF (
    input wire clk,
    input wire Re,
    input wire D,
    output reg Q
);

always @(posedge clk or posedge Re) begin
    if (Re) begin
        Q <= 1'b0; // Synchronous reset
    end else begin
        Q <= D;
    end
end
endmodule

g6/ej1/FSM.v
`include "D/DFF.v"
module FSM (
    input wire clk,
    input wire Re,
    input wire w,
    output wire z2,
    output wire z1,
    output wire z0,
    output wire z
);

wire Q2, Q1, Q0;
wire D2, D1, D0;

assign D0 = !Q0 + Q2*Q1;
assign D1 = Q1 ^ Q0;
assign D2 = Q2 + Q1*Q0;

DFF DFF0(.clk(clk), .Re(Re),.D(D0), .Q(Q0));
DFF DFF1(.clk(clk), .Re(Re), .D(D1), .Q(Q1));
DFF DFF2(.clk(clk), .Re(Re), .D(D2), .Q(Q2));

assign z2 = Q2;
assign z1 = Q1;
assign z0 = Q0;
    
endmodule

g6/ej1/FSM_tb.v


`default_nettype none
`timescale 100 ns / 10 ns

module FSM_tb();

parameter DURATION = 10;
reg clk = 0;
always #0.5 clk = ~clk;

reg  Re, w;
wire z, z2, z1 ,z0;

FSM UUT (.clk(clk), .Re(Re), .w(w), .z2(z2), .z1(z1), .z0(z0), .z(z));

integer i;

initial begin
  $dumpfile("FSM_tb.vcd");
  $dumpvars(0, FSM_tb);
  
  #5 Re = 1;
  #3;
  Re = 0;
  #5 Re = 1;
  #1;
  Re = 0;
  #(DURATION) $display("End of simulation");
  $finish;
end

endmodule

g6/ej1/FSM_tb.vcd
$date
	Sun Jun  2 19:14:38 2024
$end
$version
	Icarus Verilog
$end
$timescale
	1ps
$end
$scope module FSM_tb $end
$var wire 1 ! z $end
$var wire 1 " z2 $end
$var wire 1 # z1 $end
$var wire 1 $ z0 $end
$var parameter 32 % DURATION $end
$var reg 1 & Re $end
$var reg 1 ' clk $end
$var reg 1 ( w $end
$scope module UUT $end
$var wire 1 ) D1 $end
$var wire 1 & Re $end
$var wire 1 ' clk $end
$var wire 1 ( w $end
$var wire 1 ! z $end
$var wire 1 $ z0 $end
$var wire 1 # z1 $end
$var wire 1 " z2 $end
$var wire 1 * Q2 $end
$var wire 1 + Q1 $end
$var wire 1 , Q0 $end
$var wire 1 - D2 $end
$var wire 1 . D0 $end
$scope module DFF0 $end
$var wire 1 . D $end
$var wire 1 & Re $end
$var wire 1 ' clk $end
$var reg 1 , Q $end
$upscope $end
$scope module DFF1 $end
$var wire 1 ) D $end
$var wire 1 & Re $end
$var wire 1 ' clk $end
$var reg 1 + Q $end
$upscope $end
$scope module DFF2 $end
$var wire 1 - D $end
$var wire 1 & Re $end
$var wire 1 ' clk $end
$var reg 1 * Q $end
$upscope $end
$upscope $end
$upscope $end
$enddefinitions $end
$comment Show the parameter values. $end
$dumpall
b1010 %
$end
#0
$dumpvars
x.
x-
x,
x+
x*
x)
x(
0'
x&
x$
x#
x"
z!
$end
#50000
1'
#100000
0'
#150000
1'
#200000
0'
#250000
1'
#300000
0'
#350000
1'
#400000
0'
#450000
1'
#500000
0)
0-
1.
0"
0*
0#
0+
0$
0,
0'
1&
#550000
1'
#600000
0'
#650000
1'
#700000
0'
#750000
1'
#800000
0'
0&
#850000
1)
0.
1$
1,
1'
#900000
0'
#950000
1.
0$
0,
0-
1#
1+
1'
#1000000
0'
#1050000
0)
1-
0.
1$
1,
1'
#1100000
0'
#1150000
0$
0,
0#
0+
1-
1.
1"
1*
1'
#1200000
0'
#1250000
1)
0.
1$
1,
1'
#1300000
0)
1.
0$
0,
0-
0"
0*
0'
1&
#1350000
1'
#1400000
0'
0&
#1450000
1)
0.
1$
1,
1'
#1500000
0'
#1550000
1#
1+
1.
0$
0,
1'
#1600000
0'
#1650000
0)
1-
0.
1$
1,
1'
#1700000
0'
#1750000
1"
1*
0#
0+
1-
1.
0$
0,
1'
#1800000
0'
#1850000
1)
0.
1$
1,
1'
#1900000
0'
#1950000
1#
1+
0.
0$
0,
1'
