g4/sum_1_bit/sum_1_bit.v
module sum_1_bit (
    input wire A,
    input wire B,
    input wire Cin,
    output wire S,
    output wire Cout
);
    
assign S = (!A)*(!B)*Cin + (!A)*B*(!Cin) + A*(!B)*(!Cin) + A*B*Cin;
assign Cout = A*B+((!A)*B+A*(!B))*Cin;
endmodule

g4/sum_1_bit/sum_1_bit_tb.v
`default_nettype none
`define DUMPSTR(x) `"sum_1_bit_tb.vcd`"
`timescale 100 ns / 10 ns

module sum_1_bit_tb();

parameter DURATION = 10;
reg clk = 0;
always #0.5 clk = ~clk;

reg  a0, b0, ci;
wire s0, co;

sum_1_bit UUT (
           .A(a0),
           .B(b0),
           .Cin(ci),
           .S(s0),
           .Cout(co)
         );

integer i;
reg [2:0] i_b;

initial begin

  $dumpfile(`DUMPSTR(`VCD_OUTPUT));
  $dumpvars(0, sum_1_bit_tb);
  for (i = 0;i<8 ;i=i+1)
  begin
      i_b = i;
      a0 = i_b[2]; 
      b0 = i_b[1]; 
      ci = i_b[0]; 
      #1;      
  end


    #(DURATION) $display("End of simulation");
   $finish;
end

endmodule

g4/sum_1_bit/sum_1_bit_tb.vcd
$date
	Mon Apr 29 07:39:55 2024
$end
$version
	Icarus Verilog
$end
$timescale
	1ps
$end
$scope module sum_1_bit_tb $end
$var wire 1 ! s0 $end
$var wire 1 " co $end
$var parameter 32 # DURATION $end
$var reg 1 $ a0 $end
$var reg 1 % b0 $end
$var reg 1 & ci $end
$var reg 1 ' clk $end
$var reg 3 ( i_b [2:0] $end
$var integer 32 ) i [31:0] $end
$scope module UUT $end
$var wire 1 $ A $end
$var wire 1 % B $end
$var wire 1 & Cin $end
$var wire 1 ! S $end
$var wire 1 " Cout $end
$upscope $end
$upscope $end
$enddefinitions $end
$comment Show the parameter values. $end
$dumpall
b1010 #
$end
#0
$dumpvars
b0 )
b0 (
0'
0&
0%
0$
0"
0!
$end
#50000
1'
#100000
0'
1!
1&
b1 (
b1 )
#150000
1'
#200000
0'
0&
1!
0"
1%
b10 (
b10 )
#250000
1'
#300000
0'
0!
1"
1&
b11 (
b11 )
#350000
1'
#400000
0'
0&
0%
1!
0"
1$
b100 (
b100 )
#450000
1'
#500000
0'
0!
1"
1&
b101 (
b101 )
#550000
1'
#600000
0'
0&
0!
1"
1%
b110 (
b110 )
#650000
1'
#700000
0'
1!
1&
b111 (
b111 )
#750000
1'
#800000
0'
b1000 )
