g4/mux_8_1/mux_8_1.v
module mux_8_1(
	input wire d0,
	input wire d1,
	input wire d2,
	input wire d3,
	input wire d4,
	input wire d5,
	input wire d6,
	input wire d7,
	input wire [0:2] opt,
	output reg o0 //reg ya que se declara dentro de de un bloque procedural
);

	always @(d0 or d1 or d2 or d3 or d4 or d5 or d6 or d7 or opt)
	begin
		case(opt)
			3'b000 : o0=d0;
			3'b001 : o0=d1;
			3'b010 : o0=d2;
			3'b011 : o0=d3;
			3'b100 : o0=d4;
			3'b101 : o0=d5;
			3'b110 : o0=d6;
			3'b111 : o0=d7;
			default: o0=d0;
		endcase	
	end
endmodule

g4/mux_8_1/mux_8_1_tb.v
`default_nettype none
`define DUMPSTR(x) `"mux_8_1_tb.vcd`"
`timescale 100 ns / 10 ns

module mux_8_1_tb();

parameter DURATION = 10;
reg clk = 0;
always #0.5 clk = ~clk;

reg  i0, i1, i2, i3, i4, i5, i6, i7;
reg [0:2] opt0;
wire c0;

mux_8_1 UUT (
           .d0(i0),
           .d1(i1),
           .d2(i2),
           .d3(i3),
           .d4(i4),
           .d5(i5),
           .d6(i6),
           .d7(i7),
	   .opt(opt0),
	   .o0(c0)
           
         );

integer i, j;
reg [7:0] i_b;

initial begin

  $dumpfile(`DUMPSTR(`VCD_OUTPUT));
  $dumpvars(0, mux_8_1_tb);
  for (i = 0;i<256 ;i=i+1)
  	begin
  		for(j=0;j<8;j=j+1)
			begin
				i_b = i;
				i0 = i_b[0];
      				i1 = i_b[1];
      				i2 = i_b[2];
      				i3 = i_b[3];
     			 	i4 = i_b[4];
      				i5 = i_b[5];
      				i6 = i_b[6];
      				i7 = i_b[7];
      				opt0 = j;
      				#1;
			end	
  end


    #(DURATION) $display("End of simulation");
   $finish;
end

endmodule

g4/mux_8_1/mux_8_1_tb.vcd
$date
	Fri May 24 15:19:36 2024
$end
$version
	Icarus Verilog
$end
$timescale
	1ps
$end
$scope module mux_8_1_tb $end
$var wire 1 ! c0 $end
$var parameter 32 " DURATION $end
$var reg 1 # clk $end
$var reg 1 $ i0 $end
$var reg 1 % i1 $end
$var reg 1 & i2 $end
$var reg 1 ' i3 $end
$var reg 1 ( i4 $end
$var reg 1 ) i5 $end
$var reg 1 * i6 $end
$var reg 1 + i7 $end
$var reg 8 , i_b [7:0] $end
$var reg 3 - opt0 [0:2] $end
$var integer 32 . i [31:0] $end
$var integer 32 / j [31:0] $end
$scope module UUT $end
$var wire 1 $ d0 $end
$var wire 1 % d1 $end
$var wire 1 & d2 $end
$var wire 1 ' d3 $end
$var wire 1 ( d4 $end
$var wire 1 ) d5 $end
$var wire 1 * d6 $end
$var wire 1 + d7 $end
$var wire 3 0 opt [0:2] $end
$var reg 1 ! o0 $end
$upscope $end
$upscope $end
$enddefinitions $end
$comment Show the parameter values. $end
$dumpall
b1010 "
$end
#0
$dumpvars
b0 0
b0 /
b0 .
b0 -
b0 ,
0+
0*
0)
0(
0'
0&
0%
0$
0#
0!
$end
#50000
1#
#100000
0#
b1 -
b1 0
b1 /
#150000
1#
#200000
0#
b10 -
b10 0
b10 /
#250000
1#
#300000
0#
b11 -
b11 0
b11 /
#350000
1#
#400000
0#
b100 -
b100 0
b100 /
#450000
1#
#500000
0#
b101 -
b101 0
b101 /
#550000
1#
#600000
0#
b110 -
b110 0
b110 /
#650000
1#
#700000
0#
b111 -
b111 0
b111 /
#750000
1#
#800000
1!
0#
b0 -
b0 0
1$
b1 ,
b1 .
b0 /
#850000
1#
#900000
0!
0#
b1 -
b1 0
b1 /
#950000
1#
#1000000
0#
b10 -
b10 0
b10 /
#1050000
1#
#1100000
0#
b11 -
b11 0
b11 /
#1150000
1#
#1200000
0#
b100 -
b100 0
b100 /
#1250000
1#
#1300000
0#
b101 -
b101 0
b101 /
#1350000
1#
#1400000
0#
b110 -
b110 0
b110 /
#1450000
1#
#1500000
0#
b111 -
b111 0
b111 /
#1550000
1#
#1600000
0#
b0 -
b0 0
1%
0$
b10 ,
b10 .
b0 /
#1650000
1#
#1700000
1!
0#
b1 -
b1 0
b1 /
#1750000
1#
#1800000
0!
0#
b10 -
b10 0
b10 /
#1850000
1#
#1900000
0#
b11 -
b11 0
b11 /
#1950000
1#
#2000000
0#
b100 -
b100 0
b100 /
#2050000
1#
#2100000
0#
b101 -
b101 0
b101 /
#2150000
1#
#2200000
0#
b110 -
b110 0
b110 /
#2250000
1#
#2300000
0#
b111 -
b111 0
b111 /
#2350000
1#
#2400000
1!
0#
b0 -
b0 0
1$
b11 ,
b11 .
b0 /
#2450000
1#
#2500000
0#
b1 -
b1 0
b1 /
#2550000
1#
#2600000
0!
0#
b10 -
b10 0
b10 /
#2650000
1#
#2700000
0#
b11 -
b11 0
b11 /
#2750000
1#
#2800000
0#
b100 -
b100 0
b100 /
#2850000
1#
#2900000
0#
b101 -
b101 0
b101 /
#2950000
1#
#3000000
0#
b110 -
b110 0
b110 /
#3050000
1#
#3100000
0#
b111 -
b111 0
b111 /
#3150000
1#
#3200000
0#
b0 -
b0 0
1&
0%
0$
b100 ,
b100 .
b0 /
#3250000
1#
#3300000
0#
b1 -
b1 0
b1 /
#3350000
1#
#3400000
1!
0#
b10 -
b10 0
b10 /
#3450000
1#
#3500000
0!
0#
b11 -
b11 0
b11 /
#3550000
1#
#3600000
0#
b100 -
b100 0
b100 /
#3650000
1#
#3700000
0#
b101 -
b101 0
b101 /
#3750000
1#
#3800000
0#
b110 -
b110 0
b110 /
#3850000
1#
#3900000
0#
b111 -
b111 0
b111 /
#3950000
1#
#4000000
1!
0#
b0 -
b0 0
1$
b101 ,
b101 .
b0 /
#4050000
1#
#4100000
0!
0#
b1 -
b1 0
b1 /
#4150000
1#
#4200000
1!
0#
b10 -
b10 0
b10 /
#4250000
1#
#4300000
0!
0#
b11 -
b11 0
b11 /
#4350000
1#
#4400000
0#
b100 -
b100 0
b100 /
#4450000
1#
#4500000
0#
b101 -
b101 0
b101 /
#4550000
1#
#4600000
0#
b110 -
b110 0
b110 /
#4650000
1#
#4700000
0#
b111 -
b111 0
b111 /
#4750000
1#
#4800000
0#
b0 -
b0 0
1%
0$
b110 ,
b110 .
b0 /
#4850000
1#
#4900000
1!
0#
b1 -
b1 0
b1 /
#4950000
1#
#5000000
0#
b10 -
b10 0
b10 /
#5050000
1#
#5100000
0!
0#
b11 -
b11 0
b11 /
#5150000
1#
#5200000
0#
b100 -
b100 0
b100 /
#5250000
1#
#5300000
0#
b101 -
b101 0
b101 /
#5350000
1#
#5400000
0#
b110 -
b110 0
b110 /
#5450000
1#
#5500000
0#
b111 -
b111 0
b111 /
#5550000
1#
#5600000
1!
0#
b0 -
b0 0
1$
b111 ,
b111 .
b0 /
#5650000
1#
#5700000
0#
b1 -
b1 0
b1 /
#5750000
1#
#5800000
0#
b10 -
b10 0
b10 /
#5850000
1#
#5900000
0!
0#
b11 -
b11 0
b11 /
#5950000
1#
#6000000
0#
b100 -
b100 0
b100 /
#6050000
1#
#6100000
0#
b101 -
b101 0
b101 /
#6150000
1#
#6200000
0#
b110 -
b110 0
b110 /
#6250000
1#
#6300000
0#
b111 -
b111 0
b111 /
#6350000
1#
#6400000
0#
b0 -
b0 0
1'
0&
0%
0$
b1000 ,
b1000 .
b0 /
#6450000
1#
#6500000
0#
b1 -
b1 0
b1 /
#6550000
1#
#6600000
0#
b10 -
b10 0
b10 /
#6650000
1#
#6700000
1!
0#
b11 -
b11 0
b11 /
#6750000
1#
#6800000
0!
0#
b100 -
b100 0
b100 /
#6850000
1#
#6900000
0#
b101 -
b101 0
b101 /
#6950000
1#
#7000000
0#
b110 -
b110 0
b110 /
#7050000
1#
#7100000
0#
b111 -
b111 0
b111 /
#7150000
1#
#7200000
1!
0#
b0 -
b0 0
1$
b1001 ,
b1001 .
b0 /
#7250000
1#
#7300000
0!
0#
b1 -
b1 0
b1 /
#7350000
1#
#7400000
0#
b10 -
b10 0
b10 /
#7450000
1#
#7500000
1!
0#
b11 -
b11 0
b11 /
#7550000
1#
#7600000
0!
0#
b100 -
b100 0
b100 /
#7650000
1#
#7700000
0#
b101 -
b101 0
b101 /
#7750000
1#
#7800000
0#
b110 -
b110 0
b110 /
#7850000
1#
#7900000
0#
b111 -
b111 0
b111 /
#7950000
1#
#8000000
0#
b0 -
b0 0
1%
0$
b1010 ,
b1010 .
b0 /
#8050000
1#
#8100000
1!
0#
b1 -
b1 0
b1 /
#8150000
1#
#8200000
0!
0#
b10 -
b10 0
b10 /
#8250000
1#
#8300000
1!
0#
b11 -
b11 0
b11 /
#8350000
1#
#8400000
0!
0#
b100 -
b100 0
b100 /
#8450000
1#
#8500000
0#
b101 -
b101 0
b101 /
#8550000
1#
#8600000
0#
b110 -
b110 0
b110 /
#8650000
1#
#8700000
0#
b111 -
b111 0
b111 /
#8750000
1#
#8800000
1!
0#
b0 -
b0 0
1$
b1011 ,
b1011 .
b0 /
#8850000
1#
#8900000
0#
b1 -
b1 0
b1 /
#8950000
1#
#9000000
0!
0#
b10 -
b10 0
b10 /
#9050000
1#
#9100000
1!
0#
b11 -
b11 0
b11 /
#9150000
1#
#9200000
0!
0#
b100 -
b100 0
b100 /
#9250000
1#
#9300000
0#
b101 -
b101 0
b101 /
#9350000
1#
#9400000
0#
b110 -
b110 0
b110 /
#9450000
1#
#9500000
0#
b111 -
b111 0
b111 /
#9550000
1#
#9600000
0#
b0 -
b0 0
1&
0%
0$
b1100 ,
b1100 .
b0 /
#9650000
1#
#9700000
0#
b1 -
b1 0
b1 /
#9750000
1#
#9800000
1!
0#
b10 -
b10 0
b10 /
#9850000
1#
#9900000
0#
b11 -
b11 0
b11 /
#9950000
1#
#10000000
0!
0#
b100 -
b100 0
b100 /
#10050000
1#
#10100000
0#
b101 -
b101 0
b101 /
#10150000
1#
#10200000
0#
b110 -
b110 0
b110 /
#10250000
1#
#10300000
0#
b111 -
b111 0
b111 /
#10350000
1#
#10400000
1!
0#
b0 -
b0 0
1$
b1101 ,
b1101 .
b0 /
#10450000
1#
#10500000
0!
0#
b1 -
b1 0
b1 /
#10550000
1#
#10600000
1!
0#
b10 -
b10 0
b10 /
#10650000
1#
#10700000
0#
b11 -
b11 0
b11 /
#10750000
1#
#10800000
0!
0#
b100 -
b100 0
b100 /
#10850000
1#
#10900000
0#
b101 -
b101 0
b101 /
#10950000
1#
#11000000
0#
b110 -
b110 0
b110 /
#11050000
1#
#11100000
0#
b111 -
b111 0
b111 /
#11150000
1#
#11200000
0#
b0 -
b0 0
1%
0$
b1110 ,
b1110 .
b0 /
#11250000
1#
#11300000
1!
0#
b1 -
b1 0
b1 /
#11350000
1#
#11400000
0#
b10 -
b10 0
b10 /
#11450000
1#
#11500000
0#
b11 -
b11 0
b11 /
#11550000
1#
#11600000
0!
0#
b100 -
b100 0
b100 /
#11650000
1#
#11700000
0#
b101 -
b101 0
b101 /
#11750000
1#
#11800000
0#
b110 -
b110 0
b110 /
#11850000
1#
#11900000
0#
b111 -
b111 0
b111 /
#11950000
1#
#12000000
1!
0#
b0 -
b0 0
1$
b1111 ,
b1111 .
b0 /
#12050000
1#
#12100000
0#
b1 -
b1 0
b1 /
#12150000
1#
#12200000
0#
b10 -
b10 0
b10 /
#12250000
1#
#12300000
0#
b11 -
b11 0
b11 /
#12350000
1#
#12400000
0!
0#
b100 -
b100 0
b100 /
#12450000
1#
#12500000
0#
b101 -
b101 0
b101 /
#12550000
1#
#12600000
0#
b110 -
b110 0
b110 /
#12650000
1#
#12700000
0#
b111 -
b111 0
b111 /
#12750000
1#
#12800000
0#
b0 -
b0 0
1(
0'
0&
0%
0$
b10000 ,
b10000 .
b0 /
#12850000
1#
#12900000
0#
b1 -
b1 0
b1 /
#12950000
1#
#13000000
0#
b10 -
b10 0
b10 /
#13050000
1#
#13100000
0#
b11 -
b11 0
b11 /
#13150000
1#
#13200000
1!
0#
b100 -
b100 0
b100 /
#13250000
1#
#13300000
0!
0#
b101 -
b101 0
b101 /
#13350000
1#
#13400000
0#
b110 -
b110 0
b110 /
#13450000
1#
#13500000
0#
b111 -
b111 0
b111 /
#13550000
1#
#13600000
1!
0#
b0 -
b0 0
1$
b10001 ,
b10001 .
b0 /
#13650000
1#
#13700000
0!
0#
b1 -
b1 0
b1 /
#13750000
1#
#13800000
0#
b10 -
b10 0
b10 /
#13850000
1#
#13900000
0#
b11 -
b11 0
b11 /
#13950000
1#
#14000000
1!
0#
b100 -
b100 0
b100 /
#14050000
1#
#14100000
0!
0#
b101 -
b101 0
b101 /
#14150000
1#
#14200000
0#
b110 -
b110 0
b110 /
#14250000
1#
#14300000
0#
b111 -
b111 0
b111 /
#14350000
1#
#14400000
0#
b0 -
b0 0
1%
0$
b10010 ,
b10010 .
b0 /
#14450000
1#
#14500000
1!
0#
b1 -
b1 0
b1 /
#14550000
1#
#14600000
0!
0#
b10 -
b10 0
b10 /
#14650000
1#
#14700000
0#
b11 -
b11 0
b11 /
#14750000
1#
#14800000
1!
0#
b100 -
b100 0
b100 /
#14850000
1#
#14900000
0!
0#
b101 -
b101 0
b101 /
#14950000
1#
#15000000
0#
b110 -
b110 0
b110 /
#15050000
1#
#15100000
0#
b111 -
b111 0
b111 /
#15150000
1#
#15200000
1!
0#
b0 -
b0 0
1$
b10011 ,
b10011 .
b0 /
#15250000
1#
#15300000
0#
b1 -
b1 0
b1 /
#15350000
1#
#15400000
0!
0#
b10 -
b10 0
b10 /
#15450000
1#
#15500000
0#
b11 -
b11 0
b11 /
#15550000
1#
#15600000
1!
0#
b100 -
b100 0
b100 /
#15650000
1#
#15700000
0!
0#
b101 -
b101 0
b101 /
#15750000
1#
#15800000
0#
b110 -
b110 0
b110 /
#15850000
1#
#15900000
0#
b111 -
b111 0
b111 /
#15950000
1#
#16000000
0#
b0 -
b0 0
1&
0%
0$
b10100 ,
b10100 .
b0 /
#16050000
1#
#16100000
0#
b1 -
b1 0
b1 /
#16150000
1#
#16200000
1!
0#
b10 -
b10 0
b10 /
#16250000
1#
#16300000
0!
0#
b11 -
b11 0
b11 /
#16350000
1#
#16400000
1!
0#
b100 -
b100 0
b100 /
#16450000
1#
#16500000
0!
0#
b101 -
b101 0
b101 /
#16550000
1#
#16600000
0#
b110 -
b110 0
b110 /
#16650000
1#
#16700000
0#
b111 -
b111 0
b111 /
#16750000
1#
#16800000
1!
0#
b0 -
b0 0
1$
b10101 ,
b10101 .
b0 /
#16850000
1#
#16900000
0!
0#
b1 -
b1 0
b1 /
#16950000
1#
#17000000
1!
0#
b10 -
b10 0
b10 /
#17050000
1#
#17100000
0!
0#
b11 -
b11 0
b11 /
#17150000
1#
#17200000
1!
0#
b100 -
b100 0
b100 /
#17250000
1#
#17300000
0!
0#
b101 -
b101 0
b101 /
#17350000
1#
#17400000
0#
b110 -
b110 0
b110 /
#17450000
1#
#17500000
0#
b111 -
b111 0
b111 /
#17550000
1#
#17600000
0#
b0 -
b0 0
1%
0$
b10110 ,
b10110 .
b0 /
#17650000
1#
#17700000
1!
0#
b1 -
b1 0
b1 /
#17750000
1#
#17800000
0#
b10 -
b10 0
b10 /
#17850000
1#
#17900000
0!
0#
b11 -
b11 0
b11 /
#17950000
1#
#18000000
1!
0#
b100 -
b100 0
b100 /
#18050000
1#
#18100000
0!
0#
b101 -
b101 0
b101 /
#18150000
1#
#18200000
0#
b110 -
b110 0
b110 /
#18250000
1#
#18300000
0#
b111 -
b111 0
b111 /
#18350000
1#
#18400000
1!
0#
b0 -
b0 0
1$
b10111 ,
b10111 .
b0 /
#18450000
1#
#18500000
0#
b1 -
b1 0
b1 /
#18550000
1#
#18600000
0#
b10 -
b10 0
b10 /
#18650000
1#
#18700000
0!
0#
b11 -
b11 0
b11 /
#18750000
1#
#18800000
1!
0#
b100 -
b100 0
b100 /
#18850000
1#
#18900000
0!
0#
b101 -
b101 0
b101 /
#18950000
1#
#19000000
0#
b110 -
b110 0
b110 /
#19050000
1#
#19100000
0#
b111 -
b111 0
b111 /
#19150000
1#
#19200000
0#
b0 -
b0 0
1'
0&
0%
0$
b11000 ,
b11000 .
b0 /
#19250000
1#
#19300000
0#
b1 -
b1 0
b1 /
#19350000
1#
#19400000
0#
b10 -
b10 0
b10 /
#19450000
1#
#19500000
1!
0#
b11 -
b11 0
b11 /
#19550000
1#
#19600000
0#
b100 -
b100 0
b100 /
#19650000
1#
#19700000
0!
0#
b101 -
b101 0
b101 /
#19750000
1#
#19800000
0#
b110 -
b110 0
b110 /
#19850000
1#
#19900000
0#
b111 -
b111 0
b111 /
#19950000
1#
#20000000
1!
0#
b0 -
b0 0
1$
b11001 ,
b11001 .
b0 /
#20050000
1#
#20100000
0!
0#
b1 -
b1 0
b1 /
#20150000
1#
#20200000
0#
b10 -
b10 0
b10 /
#20250000
1#
#20300000
1!
0#
b11 -
b11 0
b11 /
#20350000
1#
#20400000
0#
b100 -
b100 0
b100 /
#20450000
1#
#20500000
0!
0#
b101 -
b101 0
b101 /
#20550000
1#
#20600000
0#
b110 -
b110 0
b110 /
#20650000
1#
#20700000
0#
b111 -
b111 0
b111 /
#20750000
1#
#20800000
0#
b0 -
b0 0
1%
0$
b11010 ,
b11010 .
b0 /
#20850000
1#
#20900000
1!
0#
b1 -
b1 0
b1 /
#20950000
1#
#21000000
0!
0#
b10 -
b10 0
b10 /
#21050000
1#
#21100000
1!
0#
b11 -
b11 0
b11 /
#21150000
1#
#21200000
0#
b100 -
b100 0
b100 /
#21250000
1#
#21300000
0!
0#
b101 -
b101 0
b101 /
#21350000
1#
#21400000
0#
b110 -
b110 0
b110 /
#21450000
1#
#21500000
0#
b111 -
b111 0
b111 /
#21550000
1#
#21600000
1!
0#
b0 -
b0 0
1$
b11011 ,
b11011 .
b0 /
#21650000
1#
#21700000
0#
b1 -
b1 0
b1 /
#21750000
1#
#21800000
0!
0#
b10 -
b10 0
b10 /
#21850000
1#
#21900000
1!
0#
b11 -
b11 0
b11 /
#21950000
1#
#22000000
0#
b100 -
b100 0
b100 /
#22050000
1#
#22100000
0!
0#
b101 -
b101 0
b101 /
#22150000
1#
#22200000
0#
b110 -
b110 0
b110 /
#22250000
1#
#22300000
0#
b111 -
b111 0
b111 /
#22350000
1#
#22400000
0#
b0 -
b0 0
1&
0%
0$
b11100 ,
b11100 .
b0 /
#22450000
1#
#22500000
0#
b1 -
b1 0
b1 /
#22550000
1#
#22600000
1!
0#
b10 -
b10 0
b10 /
#22650000
1#
#22700000
0#
b11 -
b11 0
b11 /
#22750000
1#
#22800000
0#
b100 -
b100 0
b100 /
#22850000
1#
#22900000
0!
0#
b101 -
b101 0
b101 /
#22950000
1#
#23000000
0#
b110 -
b110 0
b110 /
#23050000
1#
#23100000
0#
b111 -
b111 0
b111 /
#23150000
1#
#23200000
1!
0#
b0 -
b0 0
1$
b11101 ,
b11101 .
b0 /
#23250000
1#
#23300000
0!
0#
b1 -
b1 0
b1 /
#23350000
1#
#23400000
1!
0#
b10 -
b10 0
b10 /
#23450000
1#
#23500000
0#
b11 -
b11 0
b11 /
#23550000
1#
#23600000
0#
b100 -
b100 0
b100 /
#23650000
1#
#23700000
0!
0#
b101 -
b101 0
b101 /
#23750000
1#
#23800000
0#
b110 -
b110 0
b110 /
#23850000
1#
#23900000
0#
b111 -
b111 0
b111 /
#23950000
1#
#24000000
0#
b0 -
b0 0
1%
0$
b11110 ,
b11110 .
b0 /
#24050000
1#
#24100000
1!
0#
b1 -
b1 0
b1 /
#24150000
1#
#24200000
0#
b10 -
b10 0
b10 /
#24250000
1#
#24300000
0#
b11 -
b11 0
b11 /
#24350000
1#
#24400000
0#
b100 -
b100 0
b100 /
#24450000
1#
#24500000
0!
0#
b101 -
b101 0
b101 /
#24550000
1#
#24600000
0#
b110 -
b110 0
b110 /
#24650000
1#
#24700000
0#
b111 -
b111 0
b111 /
#24750000
1#
#24800000
1!
0#
b0 -
b0 0
1$
b11111 ,
b11111 .
b0 /
#24850000
1#
#24900000
0#
b1 -
b1 0
b1 /
#24950000
1#
#25000000
0#
b10 -
b10 0
b10 /
#25050000
1#
#25100000
0#
b11 -
b11 0
b11 /
#25150000
1#
#25200000
0#
b100 -
b100 0
b100 /
#25250000
1#
#25300000
0!
0#
b101 -
b101 0
b101 /
#25350000
1#
#25400000
0#
b110 -
b110 0
b110 /
#25450000
1#
#25500000
0#
b111 -
b111 0
b111 /
#25550000
1#
#25600000
0#
b0 -
b0 0
1)
0(
0'
0&
0%
0$
b100000 ,
b100000 .
b0 /
#25650000
1#
#25700000
0#
b1 -
b1 0
b1 /
#25750000
1#
#25800000
0#
b10 -
b10 0
b10 /
#25850000
1#
#25900000
0#
b11 -
b11 0
b11 /
#25950000
1#
#26000000
0#
b100 -
b100 0
b100 /
#26050000
1#
#26100000
1!
0#
b101 -
b101 0
b101 /
#26150000
1#
#26200000
0!
0#
b110 -
b110 0
b110 /
#26250000
1#
#26300000
0#
b111 -
b111 0
b111 /
#26350000
1#
#26400000
1!
0#
b0 -
b0 0
1$
b100001 ,
b100001 .
b0 /
#26450000
1#
#26500000
0!
0#
b1 -
b1 0
b1 /
#26550000
1#
#26600000
0#
b10 -
b10 0
b10 /
#26650000
1#
#26700000
0#
b11 -
b11 0
b11 /
#26750000
1#
#26800000
0#
b100 -
b100 0
b100 /
#26850000
1#
#26900000
1!
0#
b101 -
b101 0
b101 /
#26950000
1#
#27000000
0!
0#
b110 -
b110 0
b110 /
#27050000
1#
#27100000
0#
b111 -
b111 0
b111 /
#27150000
1#
#27200000
0#
b0 -
b0 0
1%
0$
b100010 ,
b100010 .
b0 /
#27250000
1#
#27300000
1!
0#
b1 -
b1 0
b1 /
#27350000
1#
#27400000
0!
0#
b10 -
b10 0
b10 /
#27450000
1#
#27500000
0#
b11 -
b11 0
b11 /
#27550000
1#
#27600000
0#
b100 -
b100 0
b100 /
#27650000
1#
#27700000
1!
0#
b101 -
b101 0
b101 /
#27750000
1#
#27800000
0!
0#
b110 -
b110 0
b110 /
#27850000
1#
#27900000
0#
b111 -
b111 0
b111 /
#27950000
1#
#28000000
1!
0#
b0 -
b0 0
1$
b100011 ,
b100011 .
b0 /
#28050000
1#
#28100000
0#
b1 -
b1 0
b1 /
#28150000
1#
#28200000
0!
0#
b10 -
b10 0
b10 /
#28250000
1#
#28300000
0#
b11 -
b11 0
b11 /
#28350000
1#
#28400000
0#
b100 -
b100 0
b100 /
#28450000
1#
#28500000
1!
0#
b101 -
b101 0
b101 /
#28550000
1#
#28600000
0!
0#
b110 -
b110 0
b110 /
#28650000
1#
#28700000
0#
b111 -
b111 0
b111 /
#28750000
1#
#28800000
0#
b0 -
b0 0
1&
0%
0$
b100100 ,
b100100 .
b0 /
#28850000
1#
#28900000
0#
b1 -
b1 0
b1 /
#28950000
1#
#29000000
1!
0#
b10 -
b10 0
b10 /
#29050000
1#
#29100000
0!
0#
b11 -
b11 0
b11 /
#29150000
1#
#29200000
0#
b100 -
b100 0
b100 /
#29250000
1#
#29300000
1!
0#
b101 -
b101 0
b101 /
#29350000
1#
#29400000
0!
0#
b110 -
b110 0
b110 /
#29450000
1#
#29500000
0#
b111 -
b111 0
b111 /
#29550000
1#
#29600000
1!
0#
b0 -
b0 0
1$
b100101 ,
b100101 .
b0 /
#29650000
1#
#29700000
0!
0#
b1 -
b1 0
b1 /
#29750000
1#
#29800000
1!
0#
b10 -
b10 0
b10 /
#29850000
1#
#29900000
0!
0#
b11 -
b11 0
b11 /
#29950000
1#
#30000000
0#
b100 -
b100 0
b100 /
#30050000
1#
#30100000
1!
0#
b101 -
b101 0
b101 /
#30150000
1#
#30200000
0!
0#
b110 -
b110 0
b110 /
#30250000
1#
#30300000
0#
b111 -
b111 0
b111 /
#30350000
1#
#30400000
0#
b0 -
b0 0
1%
0$
b100110 ,
b100110 .
b0 /
#30450000
1#
#30500000
1!
0#
b1 -
b1 0
b1 /
#30550000
1#
#30600000
0#
b10 -
b10 0
b10 /
#30650000
1#
#30700000
0!
0#
b11 -
b11 0
b11 /
#30750000
1#
#30800000
0#
b100 -
b100 0
b100 /
#30850000
1#
#30900000
1!
0#
b101 -
b101 0
b101 /
#30950000
1#
#31000000
0!
0#
b110 -
b110 0
b110 /
#31050000
1#
#31100000
0#
b111 -
b111 0
b111 /
#31150000
1#
#31200000
1!
0#
b0 -
b0 0
1$
b100111 ,
b100111 .
b0 /
#31250000
1#
#31300000
0#
b1 -
b1 0
b1 /
#31350000
1#
#31400000
0#
b10 -
b10 0
b10 /
#31450000
1#
#31500000
0!
0#
b11 -
b11 0
b11 /
#31550000
1#
#31600000
0#
b100 -
b100 0
b100 /
#31650000
1#
#31700000
1!
0#
b101 -
b101 0
b101 /
#31750000
1#
#31800000
0!
0#
b110 -
b110 0
b110 /
#31850000
1#
#31900000
0#
b111 -
b111 0
b111 /
#31950000
1#
#32000000
0#
b0 -
b0 0
1'
0&
0%
0$
b101000 ,
b101000 .
b0 /
#32050000
1#
#32100000
0#
b1 -
b1 0
b1 /
#32150000
1#
#32200000
0#
b10 -
b10 0
b10 /
#32250000
1#
#32300000
1!
0#
b11 -
b11 0
b11 /
#32350000
1#
#32400000
0!
0#
b100 -
b100 0
b100 /
#32450000
1#
#32500000
1!
0#
b101 -
b101 0
b101 /
#32550000
1#
#32600000
0!
0#
b110 -
b110 0
b110 /
#32650000
1#
#32700000
0#
b111 -
b111 0
b111 /
#32750000
1#
#32800000
1!
0#
b0 -
b0 0
1$
b101001 ,
b101001 .
b0 /
#32850000
1#
#32900000
0!
0#
b1 -
b1 0
b1 /
#32950000
1#
#33000000
0#
b10 -
b10 0
b10 /
#33050000
1#
#33100000
1!
0#
b11 -
b11 0
b11 /
#33150000
1#
#33200000
0!
0#
b100 -
b100 0
b100 /
#33250000
1#
#33300000
1!
0#
b101 -
b101 0
b101 /
#33350000
1#
#33400000
0!
0#
b110 -
b110 0
b110 /
#33450000
1#
#33500000
0#
b111 -
b111 0
b111 /
#33550000
1#
#33600000
0#
b0 -
b0 0
1%
0$
b101010 ,
b101010 .
b0 /
#33650000
1#
#33700000
1!
0#
b1 -
b1 0
b1 /
#33750000
1#
#33800000
0!
0#
b10 -
b10 0
b10 /
#33850000
1#
#33900000
1!
0#
b11 -
b11 0
b11 /
#33950000
1#
#34000000
0!
0#
b100 -
b100 0
b100 /
#34050000
1#
#34100000
1!
0#
b101 -
b101 0
b101 /
#34150000
1#
#34200000
0!
0#
b110 -
b110 0
b110 /
#34250000
1#
#34300000
0#
b111 -
b111 0
b111 /
#34350000
1#
#34400000
1!
0#
b0 -
b0 0
1$
b101011 ,
b101011 .
b0 /
#34450000
1#
#34500000
0#
b1 -
b1 0
b1 /
#34550000
1#
#34600000
0!
0#
b10 -
b10 0
b10 /
#34650000
1#
#34700000
1!
0#
b11 -
b11 0
b11 /
#34750000
1#
#34800000
0!
0#
b100 -
b100 0
b100 /
#34850000
1#
#34900000
1!
0#
b101 -
b101 0
b101 /
#34950000
1#
#35000000
0!
0#
b110 -
b110 0
b110 /
#35050000
1#
#35100000
0#
b111 -
b111 0
b111 /
#35150000
1#
#35200000
0#
b0 -
b0 0
1&
0%
0$
b101100 ,
b101100 .
b0 /
#35250000
1#
#35300000
0#
b1 -
b1 0
b1 /
#35350000
1#
#35400000
1!
0#
b10 -
b10 0
b10 /
#35450000
1#
#35500000
0#
b11 -
b11 0
b11 /
#35550000
1#
#35600000
0!
0#
b100 -
b100 0
b100 /
#35650000
1#
#35700000
1!
0#
b101 -
b101 0
b101 /
#35750000
1#
#35800000
0!
0#
b110 -
b110 0
b110 /
#35850000
1#
#35900000
0#
b111 -
b111 0
b111 /
#35950000
1#
#36000000
1!
0#
b0 -
b0 0
1$
b101101 ,
b101101 .
b0 /
#36050000
1#
#36100000
0!
0#
b1 -
b1 0
b1 /
#36150000
1#
#36200000
1!
0#
b10 -
b10 0
b10 /
#36250000
1#
#36300000
0#
b11 -
b11 0
b11 /
#36350000
1#
#36400000
0!
0#
b100 -
b100 0
b100 /
#36450000
1#
#36500000
1!
0#
b101 -
b101 0
b101 /
#36550000
1#
#36600000
0!
0#
b110 -
b110 0
b110 /
#36650000
1#
#36700000
0#
b111 -
b111 0
b111 /
#36750000
1#
#36800000
0#
b0 -
b0 0
1%
0$
b101110 ,
b101110 .
b0 /
#36850000
1#
#36900000
1!
0#
b1 -
b1 0
b1 /
#36950000
1#
#37000000
0#
b10 -
b10 0
b10 /
#37050000
1#
#37100000
0#
b11 -
b11 0
b11 /
#37150000
1#
#37200000
0!
0#
b100 -
b100 0
b100 /
#37250000
1#
#37300000
1!
0#
b101 -
b101 0
b101 /
#37350000
1#
#37400000
0!
0#
b110 -
b110 0
b110 /
#37450000
1#
#37500000
0#
b111 -
b111 0
b111 /
#37550000
1#
#37600000
1!
0#
b0 -
b0 0
1$
b101111 ,
b101111 .
b0 /
#37650000
1#
#37700000
0#
b1 -
b1 0
b1 /
#37750000
1#
#37800000
0#
b10 -
b10 0
b10 /
#37850000
1#
#37900000
0#
b11 -
b11 0
b11 /
#37950000
1#
#38000000
0!
0#
b100 -
b100 0
b100 /
#38050000
1#
#38100000
1!
0#
b101 -
b101 0
b101 /
#38150000
1#
#38200000
0!
0#
b110 -
b110 0
b110 /
#38250000
1#
#38300000
0#
b111 -
b111 0
b111 /
#38350000
1#
#38400000
0#
b0 -
b0 0
1(
0'
0&
0%
0$
b110000 ,
b110000 .
b0 /
#38450000
1#
#38500000
0#
b1 -
b1 0
b1 /
#38550000
1#
#38600000
0#
b10 -
b10 0
b10 /
#38650000
1#
#38700000
0#
b11 -
b11 0
b11 /
#38750000
1#
#38800000
1!
0#
b100 -
b100 0
b100 /
#38850000
1#
#38900000
0#
b101 -
b101 0
b101 /
#38950000
1#
#39000000
0!
0#
b110 -
b110 0
b110 /
#39050000
1#
