g5/xDFF/D/DFF.v
module DFF (
    input wire clk,
    input wire D,
    output reg Q
);


always @(negedge clk)  begin
    /* case (D)
        1'b0 : Q <=1'b0; 
        1'b1 : Q <=1'b1; 
    endcase; */
    Q <= D;


end
endmodule

g5/xDFF/xDFF.v
`include "D/DFF.v"
module xDFF (
    input wire clk0,
    input wire D0,
    input wire Ra,
    input wire S,
    input wire Rs,
    input wire en,
    output reg Q0
);

wire tmp_q0;

DFF DFF0 (
    .clk(clk0),
    .D(D0),
    .Q(tmp_q0)
);

always @(posedge clk0 or posedge Ra or posedge S) begin
    if (Ra) begin
        Q0 <= 0; // Asynchronous reset
    end else if (S) begin
        Q0 <= 1; // Asynchronous set
    end else begin
        if (Rs) begin
            Q0 <= 0; // Synchronous reset
        end else begin
            if (en) begin //enable 
                 Q0 <= tmp_q0; // Normal operation     
            end
           end
    end
end

/* 
always @(posedge clk0){
    if(Rs) begin
        Q0 <= 1;
    end else begin
        Q0 <= tmp_q0;
    end
}


always @(posedge Ra) begin
    if (Ra) begin
        Q0 <= 0;
    end
end

always  @(posedge S) begin
    if (S) begin
        Q0 <= 1;
    end
end

 */
 endmodule

g5/xDFF/xDFF_tb.v

`default_nettype none
`timescale 100 ns / 10 ns

module xDFF_tb();

parameter DURATION = 10;
reg clk0 = 0;
always #0.5 clk0 = ~clk0;

reg  d0,ra0,s0,rs0,en0;
wire q0;

xDFF UUT (.clk0(clk0), .D0(d0), .Ra(ra0), 
    .S(s0), .Rs(rs0), .en(en0), .Q0(q0));
integer i;

initial begin
  // Directly specify the VCD file name without using macros
  $dumpfile("xDFF_tb.vcd");
  // Dump variables for the jk_tb module
  $dumpvars(0, xDFF_tb);

   for (i = 0; i < 2 ; i = i + 1) begin
    d0 = i;
    #1;
    end
    #2
    ra0 = 1;

    en0 = 1;
    ra0 = 0;
   for (i = 0; i < 2 ; i = i + 1) begin
    d0 = i;
    #1;
    end
    #2
    ra0 = 1;
    
  #(DURATION) $display("End of simulation");
  $finish;
end

endmodule

g5/xDFF/xDFF_tb.vcd
$date
	Wed May 29 08:28:06 2024
$end
$version
	Icarus Verilog
$end
$timescale
	1ps
$end
$scope module xDFF_tb $end
$var wire 1 ! q0 $end
$var parameter 32 " DURATION $end
$var reg 1 # clk0 $end
$var reg 1 $ d0 $end
$var reg 1 % en0 $end
$var reg 1 & ra0 $end
$var reg 1 ' rs0 $end
$var reg 1 ( s0 $end
$var integer 32 ) i [31:0] $end
$scope module UUT $end
$var wire 1 $ D0 $end
$var wire 1 & Ra $end
$var wire 1 ' Rs $end
$var wire 1 ( S $end
$var wire 1 # clk0 $end
$var wire 1 % en $end
$var wire 1 * tmp_q0 $end
$var reg 1 ! Q0 $end
$scope module DFF0 $end
$var wire 1 $ D $end
$var wire 1 # clk $end
$var reg 1 * Q $end
$upscope $end
$upscope $end
$upscope $end
$enddefinitions $end
$comment Show the parameter values. $end
$dumpall
b1010 "
$end
#0
$dumpvars
0*
b0 )
x(
x'
x&
x%
0$
0#
x!
$end
#50000
1#
#100000
1*
0#
1$
b1 )
#150000
1#
#200000
0#
b10 )
#250000
1#
#300000
0#
#350000
1#
#400000
0*
1!
0#
0$
b0 )
1%
0&
#450000
0!
1#
#500000
1*
0#
1$
b1 )
#550000
1!
1#
#600000
0#
b10 )
#650000
1#
#700000
0#
#750000
1#
#800000
0!
0#
1&
