tpi/tpi.v
module tpi (
    input wire clk,
    input wire Re,
    output reg speaker
);

reg [14:0] counter;
always @(posedge Re ) begin
    counter = 0;
    speaker = 0;
end

always @(posedge clk ) begin
    if (counter == 27272)
        counter <= 0;
    else
       counter <=counter+1;
end

always @(posedge clk ) begin
    if(counter == 27272)
        speaker <= ~speaker;
end
    
endmodule

tpi/tpi_tb.v
`default_nettype none
`timescale 1 ns / 100 ps

module tpi_tb();

parameter DURATION = 3000000;
reg clk = 0;
always #41.667 clk = ~clk;

reg Re;
wire speaker;

tpi UUT (.clk(clk), .Re(Re), .speaker(speaker));

initial begin
  $dumpfile("tpi_tb.vcd");
  $dumpvars(0, tpi_tb);
  Re = 1;
  
  
  #(DURATION) $display("End of simulation");
  $finish;
end

endmodule

tpi/tpi_tb.vcd
$date
	Sun Jun  9 13:47:27 2024
$end
$version
	Icarus Verilog
$end
$timescale
	1ps
$end
$scope module tpi_tb $end
$var wire 1 ! speaker $end
$var parameter 32 " DURATION $end
$var reg 1 # Re $end
$var reg 1 $ clk $end
$scope module UUT $end
$var wire 1 # Re $end
$var wire 1 $ clk $end
$var reg 15 % counter [14:0] $end
$var reg 1 ! speaker $end
$upscope $end
$upscope $end
$enddefinitions $end
$comment Show the parameter values. $end
$dumpall
b1011011100011011000000 "
$end
#0
$dumpvars
b0 %
0$
1#
0!
$end
#41700
b1 %
1$
#83400
0$
#125100
b10 %
1$
#166800
0$
#208500
b11 %
1$
#250200
0$
#291900
b100 %
1$
#333600
0$
#375300
b101 %
1$
#417000
0$
#458700
b110 %
1$
#500400
0$
#542100
b111 %
1$
#583800
0$
#625500
b1000 %
1$
#667200
0$
#708900
b1001 %
1$
#750600
0$
#792300
b1010 %
1$
#834000
0$
#875700
b1011 %
1$
#917400
0$
#959100
b1100 %
1$
#1000800
0$
#1042500
b1101 %
1$
#1084200
0$
#1125900
b1110 %
1$
#1167600
0$
#1209300
b1111 %
1$
#1251000
0$
#1292700
b10000 %
1$
#1334400
0$
#1376100
b10001 %
1$
#1417800
0$
#1459500
b10010 %
1$
#1501200
0$
#1542900
b10011 %
1$
#1584600
0$
#1626300
b10100 %
1$
#1668000
0$
#1709700
b10101 %
1$
#1751400
0$
#1793100
b10110 %
1$
#1834800
0$
#1876500
b10111 %
1$
#1918200
0$
#1959900
b11000 %
1$
#2001600
0$
#2043300
b11001 %
1$
#2085000
0$
#2126700
b11010 %
1$
#2168400
0$
#2210100
b11011 %
1$
#2251800
0$
#2293500
b11100 %
1$
#2335200
0$
#2376900
b11101 %
1$
#2418600
0$
#2460300
b11110 %
1$
#2502000
0$
#2543700
b11111 %
1$
#2585400
0$
#2627100
b100000 %
1$
#2668800
0$
#2710500
b100001 %
1$
#2752200
0$
#2793900
b100010 %
1$
#2835600
0$
#2877300
b100011 %
1$
#2919000
0$
#2960700
b100100 %
1$
#3002400
0$
#3044100
b100101 %
1$
#3085800
0$
#3127500
b100110 %
1$
#3169200
0$
#3210900
b100111 %
1$
#3252600
0$
#3294300
b101000 %
1$
#3336000
0$
#3377700
b101001 %
1$
#3419400
0$
#3461100
b101010 %
1$
#3502800
0$
#3544500
b101011 %
1$
#3586200
0$
#3627900
b101100 %
1$
#3669600
0$
#3711300
b101101 %
1$
#3753000
0$
#3794700
b101110 %
1$
#3836400
0$
#3878100
b101111 %
1$
#3919800
0$
#3961500
b110000 %
1$
#4003200
0$
#4044900
b110001 %
1$
#4086600
0$
#4128300
b110010 %
1$
#4170000
0$
#4211700
b110011 %
1$
#4253400
0$
#4295100
b110100 %
1$
#4336800
0$
#4378500
b110101 %
1$
#4420200
0$
#4461900
b110110 %
1$
#4503600
0$
#4545300
b110111 %
1$
#4587000
0$
#4628700
b111000 %
1$
#4670400
0$
#4712100
b111001 %
1$
#4753800
0$
#4795500
b111010 %
1$
#4837200
0$
#4878900
b111011 %
1$
#4920600
0$
#4962300
b111100 %
1$
#5004000
0$
#5045700
b111101 %
1$
#5087400
0$
#5129100
b111110 %
1$
#5170800
0$
#5212500
b111111 %
1$
#5254200
0$
#5295900
b1000000 %
1$
#5337600
0$
#5379300
b1000001 %
1$
#5421000
0$
#5462700
b1000010 %
1$
#5504400
0$
#5546100
b1000011 %
1$
#5587800
0$
#5629500
b1000100 %
1$
#5671200
0$
#5712900
b1000101 %
1$
#5754600
0$
#5796300
b1000110 %
1$
#5838000
0$
#5879700
b1000111 %
1$
#5921400
0$
#5963100
b1001000 %
1$
#6004800
0$
#6046500
b1001001 %
1$
#6088200
0$
#6129900
b1001010 %
1$
#6171600
0$
#6213300
b1001011 %
1$
#6255000
0$
#6296700
b1001100 %
1$
#6338400
0$
#6380100
b1001101 %
1$
#6421800
0$
#6463500
b1001110 %
1$
#6505200
0$
#6546900
b1001111 %
1$
#6588600
0$
#6630300
b1010000 %
1$
#6672000
0$
#6713700
b1010001 %
1$
#6755400
0$
#6797100
b1010010 %
1$
#6838800
0$
#6880500
b1010011 %
1$
#6922200
0$
#6963900
b1010100 %
1$
#7005600
0$
#7047300
b1010101 %
1$
#7089000
0$
#7130700
b1010110 %
1$
#7172400
0$
#7214100
b1010111 %
1$
#7255800
0$
#7297500
b1011000 %
1$
#7339200
0$
#7380900
b1011001 %
1$
#7422600
0$
#7464300
b1011010 %
1$
#7506000
0$
#7547700
b1011011 %
1$
#7589400
0$
#7631100
b1011100 %
1$
#7672800
0$
#7714500
b1011101 %
1$
#7756200
0$
#7797900
b1011110 %
1$
#7839600
0$
#7881300
b1011111 %
1$
#7923000
0$
#7964700
b1100000 %
1$
#8006400
0$
#8048100
b1100001 %
1$
#8089800
0$
#8131500
b1100010 %
1$
#8173200
0$
#8214900
b1100011 %
1$
#8256600
0$
#8298300
b1100100 %
1$
#8340000
0$
#8381700
b1100101 %
1$
#8423400
0$
#8465100
b1100110 %
1$
#8506800
0$
#8548500
b1100111 %
1$
#8590200
0$
#8631900
b1101000 %
1$
#8673600
0$
#8715300
b1101001 %
1$
#8757000
0$
#8798700
b1101010 %
1$
#8840400
0$
#8882100
b1101011 %
1$
#8923800
0$
#8965500
b1101100 %
1$
#9007200
0$
#9048900
b1101101 %
1$
#9090600
0$
#9132300
b1101110 %
1$
#9174000
0$
#9215700
b1101111 %
1$
#9257400
0$
#9299100
b1110000 %
1$
#9340800
0$
#9382500
b1110001 %
1$
#9424200
0$
#9465900
b1110010 %
1$
#9507600
0$
#9549300
b1110011 %
1$
#9591000
0$
#9632700
b1110100 %
1$
#9674400
0$
#9716100
b1110101 %
1$
#9757800
0$
#9799500
b1110110 %
1$
#9841200
0$
#9882900
b1110111 %
1$
#9924600
0$
#9966300
b1111000 %
1$
#10008000
0$
#10049700
b1111001 %
1$
#10091400
0$
#10133100
b1111010 %
1$
#10174800
0$
#10216500
b1111011 %
1$
#10258200
0$
#10299900
b1111100 %
1$
#10341600
0$
#10383300
b1111101 %
1$
#10425000
0$
#10466700
b1111110 %
1$
#10508400
0$
#10550100
b1111111 %
1$
#10591800
0$
#10633500
b10000000 %
1$
#10675200
0$
#10716900
b10000001 %
1$
#10758600
0$
#10800300
b10000010 %
1$
#10842000
0$
#10883700
b10000011 %
1$
#10925400
0$
#10967100
b10000100 %
1$
#11008800
0$
#11050500
b10000101 %
1$
#11092200
0$
#11133900
b10000110 %
1$
#11175600
0$
#11217300
b10000111 %
1$
#11259000
0$
#11300700
b10001000 %
1$
#11342400
0$
#11384100
b10001001 %
1$
#11425800
0$
#11467500
b10001010 %
1$
#11509200
0$
#11550900
b10001011 %
1$
#11592600
0$
#11634300
b10001100 %
1$
#11676000
0$
#11717700
b10001101 %
1$
#11759400
0$
#11801100
b10001110 %
1$
#11842800
0$
#11884500
b10001111 %
1$
#11926200
0$
#11967900
b10010000 %
1$
#12009600
0$
#12051300
b10010001 %
1$
#12093000
0$
#12134700
b10010010 %
1$
#12176400
0$
#12218100
b10010011 %
1$
#12259800
0$
#12301500
b10010100 %
1$
#12343200
0$
#12384900
b10010101 %
1$
#12426600
0$
#12468300
b10010110 %
1$
#12510000
0$
#12551700
b10010111 %
1$
#12593400
0$
#12635100
b10011000 %
1$
#12676800
0$
#12718500
b10011001 %
1$
#12760200
0$
#12801900
b10011010 %
1$
#12843600
0$
#12885300
b10011011 %
1$
#12927000
0$
#12968700
b10011100 %
1$
#13010400
0$
#13052100
b10011101 %
1$
#13093800
0$
#13135500
b10011110 %
1$
#13177200
0$
#13218900
b10011111 %
1$
#13260600
0$
#13302300
b10100000 %
1$
#13344000
0$
#13385700
b10100001 %
1$
#13427400
0$
#13469100
b10100010 %
1$
#13510800
0$
#13552500
b10100011 %
1$
#13594200
0$
#13635900
b10100100 %
1$
#13677600
0$
#13719300
b10100101 %
1$
#13761000
0$
#13802700
b10100110 %
1$
#13844400
0$
#13886100
b10100111 %
1$
#13927800
0$
#13969500
b10101000 %
1$
#14011200
0$
#14052900
b10101001 %
1$
#14094600
0$
#14136300
b10101010 %
1$
#14178000
0$
#14219700
b10101011 %
1$
#14261400
0$
#14303100
b10101100 %
1$
#14344800
0$
#14386500
b10101101 %
1$
#14428200
0$
#14469900
b10101110 %
1$
#14511600
0$
#14553300
b10101111 %
1$
#14595000
0$
#14636700
b10110000 %
1$
#14678400
0$
#14720100
b10110001 %
1$
#14761800
0$
#14803500
b10110010 %
1$
#14845200
0$
#14886900
b10110011 %
1$
#14928600
0$
#14970300
b10110100 %
1$
#15012000
0$
#15053700
b10110101 %
1$
#15095400
0$
#15137100
b10110110 %
1$
#15178800
0$
#15220500
b10110111 %
1$
#15262200
0$
#15303900
b10111000 %
1$
#15345600
0$
#15387300
b10111001 %
1$
#15429000
0$
#15470700
b10111010 %
1$
#15512400
0$
#15554100
b10111011 %
1$
#15595800
0$
#15637500
b10111100 %
1$
#15679200
0$
#15720900
b10111101 %
1$
#15762600
0$
#15804300
b10111110 %
1$
#15846000
0$
#15887700
b10111111 %
1$
#15929400
0$
#15971100
b11000000 %
1$
#16012800
0$
#16054500
b11000001 %
1$
#16096200
0$
#16137900
b11000010 %
1$
#16179600
0$
#16221300
b11000011 %
1$
#16263000
0$
#16304700
b11000100 %
1$
#16346400
0$
#16388100
b11000101 %
1$
#16429800
0$
#16471500
b11000110 %
1$
#16513200
0$
#16554900
b11000111 %
1$
#16596600
0$
#16638300
b11001000 %
1$
#16680000
0$
#16721700
b11001001 %
1$
#16763400
0$
#16805100
b11001010 %
1$
#16846800
0$
#16888500
b11001011 %
1$
#16930200
0$
#16971900
b11001100 %
1$
#17013600
0$
#17055300
b11001101 %
1$
#17097000
0$
#17138700
b11001110 %
1$
#17180400
0$
#17222100
b11001111 %
1$
#17263800
0$
#17305500
b11010000 %
1$
#17347200
0$
#17388900
b11010001 %
1$
#17430600
0$
#17472300
b11010010 %
1$
#17514000
0$
#17555700
b11010011 %
1$
#17597400
0$
#17639100
b11010100 %
1$
#17680800
0$
#17722500
b11010101 %
1$
#17764200
0$
#17805900
b11010110 %
1$
#17847600
0$
#17889300
b11010111 %
1$
#17931000
0$
#17972700
b11011000 %
1$
#18014400
0$
#18056100
b11011001 %
1$
#18097800
0$
#18139500
b11011010 %
1$
#18181200
0$
#18222900
b11011011 %
1$
#18264600
0$
#18306300
b11011100 %
1$
#18348000
0$
#18389700
b11011101 %
1$
#18431400
0$
#18473100
b11011110 %
1$
#18514800
0$
#18556500
b11011111 %
1$
#18598200
0$
#18639900
b11100000 %
1$
#18681600
0$
#18723300
b11100001 %
1$
#18765000
0$
#18806700
b11100010 %
1$
#18848400
0$
#18890100
b11100011 %
1$
#18931800
0$
#18973500
b11100100 %
1$
#19015200
0$
#19056900
b11100101 %
1$
#19098600
0$
#19140300
b11100110 %
1$
#19182000
0$
#19223700
b11100111 %
1$
#19265400
0$
#19307100
b11101000 %
1$
#19348800
0$
#19390500
b11101001 %
1$
#19432200
0$
#19473900
b11101010 %
1$
#19515600
0$
#19557300
b11101011 %
1$
#19599000
0$
#19640700
b11101100 %
1$
#19682400
0$
#19724100
b11101101 %
1$
#19765800
0$
#19807500
b11101110 %
1$
#19849200
0$
#19890900
b11101111 %
1$
#19932600
0$
#19974300
b11110000 %
1$
#20016000
0$
#20057700
b11110001 %
1$
#20099400
0$
#20141100
b11110010 %
1$
#20182800
0$
#20224500
b11110011 %
1$
#20266200
0$
#20307900
b11110100 %
1$
#20349600
0$
#20391300
b11110101 %
1$
#20433000
0$
#20474700
b11110110 %
1$
#20516400
0$
#20558100
b11110111 %
1$
#20599800
0$
#20641500
b11111000 %
1$
#20683200
0$
#20724900
b11111001 %
1$
#20766600
0$
#20808300
b11111010 %
1$
#20850000
0$
#20891700
b11111011 %
1$
#20933400
0$
#20975100
b11111100 %
1$
#21016800
0$
#21058500
b11111101 %
1$
#21100200
0$
#21141900
b11111110 %
1$
#21183600
0$
#21225300
b11111111 %
1$
#21267000
0$
#21308700
b100000000 %
1$
#21350400
0$
#21392100
b100000001 %
1$
#21433800
0$
#21475500
b100000010 %
1$
#21517200
0$
#21558900
b100000011 %
1$
#21600600
0$
#21642300
b100000100 %
1$
#21684000
0$
#21725700
b100000101 %
1$
#21767400
0$
#21809100
b100000110 %
1$
#21850800
0$
#21892500
b100000111 %
1$
#21934200
0$
#21975900
b100001000 %
1$
#22017600
0$
#22059300
b100001001 %
1$
#22101000
0$
#22142700
b100001010 %
1$
#22184400
0$
#22226100
b100001011 %
1$
#22267800
0$
#22309500
b100001100 %
1$
#22351200
0$
#22392900
b100001101 %
1$
#22434600
0$
#22476300
b100001110 %
1$
#22518000
0$
#22559700
b100001111 %
1$
#22601400
0$
#22643100
b100010000 %
1$
#22684800
0$
#22726500
b100010001 %
1$
#22768200
0$
#22809900
b100010010 %
1$
#22851600
0$
#22893300
b100010011 %
1$
#22935000
0$
#22976700
b100010100 %
1$
#23018400
0$
#23060100
b100010101 %
1$
#23101800
0$
#23143500
b100010110 %
1$
#23185200
0$
#23226900
b100010111 %
1$
#23268600
0$
#23310300
b100011000 %
1$
#23352000
0$
#23393700
b100011001 %
1$
#23435400
0$
#23477100
b100011010 %
1$
#23518800
0$
#23560500
b100011011 %
1$
#23602200
0$
#23643900
b100011100 %
1$
#23685600
0$
#23727300
b100011101 %
1$
#23769000
0$
#23810700
b100011110 %
1$
#23852400
0$
#23894100
b100011111 %
1$
#23935800
0$
#23977500
b100100000 %
1$
#24019200
0$
#24060900
b100100001 %
1$
#24102600
0$
#24144300
b100100010 %
1$
#24186000
0$
#24227700
b100100011 %
1$
#24269400
0$
#24311100
b100100100 %
1$
#24352800
0$
#24394500
b100100101 %
1$
#24436200
0$
#24477900
b100100110 %
1$
#24519600
0$
#24561300
b100100111 %
1$
#24603000
0$
#24644700
b100101000 %
1$
#24686400
0$
#24728100
b100101001 %
1$
#24769800
0$
#24811500
b100101010 %
1$
#24853200
0$
#24894900
b100101011 %
1$
#24936600
0$
#24978300
b100101100 %
1$
#25020000
0$
#25061700
b100101101 %
1$
#25103400
0$
#25145100
b100101110 %
1$
#25186800
0$
#25228500
b100101111 %
1$
#25270200
0$
#25311900
b100110000 %
1$
#25353600
0$
#25395300
b100110001 %
1$
#25437000
0$
#25478700
b100110010 %
1$
#25520400
0$
#25562100
b100110011 %
1$
#25603800
0$
#25645500
b100110100 %
1$
#25687200
0$
#25728900
b100110101 %
1$
#25770600
0$
#25812300
b100110110 %
1$
#25854000
0$
#25895700
b100110111 %
1$
#25937400
0$
#25979100
b100111000 %
1$
#26020800
0$
#26062500
b100111001 %
1$
#26104200
0$
#26145900
b100111010 %
1$
#26187600
0$
#26229300
b100111011 %
1$
#26271000
0$
#26312700
b100111100 %
1$
#26354400
0$
#26396100
b100111101 %
1$
#26437800
0$
#26479500
b100111110 %
1$
#26521200
0$
#26562900
b100111111 %
1$
#26604600
0$
#26646300
b101000000 %
1$
#26688000
0$
#26729700
b101000001 %
1$
#26771400
0$
#26813100
b101000010 %
1$
#26854800
0$
#26896500
b101000011 %
1$
#26938200
0$
#26979900
b101000100 %
1$
#27021600
0$
#27063300
b101000101 %
1$
#27105000
0$
#27146700
b101000110 %
1$
#27188400
0$
#27230100
b101000111 %
1$
#27271800
0$
#27313500
b101001000 %
1$
#27355200
0$
#27396900
b101001001 %
1$
#27438600
0$
#27480300
b101001010 %
1$
#27522000
0$
#27563700
b101001011 %
1$
#27605400
0$
#27647100
b101001100 %
1$
#27688800
0$
#27730500
b101001101 %
1$
#27772200
0$
#27813900
b101001110 %
1$
#27855600
0$
#27897300
b101001111 %
1$
#27939000
0$
#27980700
b101010000 %
1$
#28022400
0$
#28064100
b101010001 %
1$
#28105800
0$
#28147500
b101010010 %
1$
#28189200
0$
#28230900
b101010011 %
1$
#28272600
0$
#28314300
b101010100 %
1$
#28356000
0$
#28397700
b101010101 %
1$
#28439400
0$
#28481100
b101010110 %
1$
#28522800
0$
#28564500
b101010111 %
1$
#28606200
0$
#28647900
b101011000 %
1$
#28689600
0$
#28731300
b101011001 %
1$
#28773000
0$
#28814700
b101011010 %
1$
#28856400
0$
#28898100
b101011011 %
1$
#28939800
0$
#28981500
b101011100 %
1$
#29023200
0$
#29064900
b101011101 %
1$
#29106600
0$
#29148300
b101011110 %
1$
#29190000
0$
#29231700
b101011111 %
1$
#29273400
0$
#29315100
b101100000 %
1$
#29356800
0$
#29398500
b101100001 %
1$
#29440200
0$
#29481900
b101100010 %
1$
#29523600
0$
#29565300
b101100011 %
1$
#29607000
0$
#29648700
b101100100 %
1$
#29690400
0$
#29732100
b101100101 %
1$
#29773800
0$
#29815500
b101100110 %
1$
#29857200
0$
#29898900
b101100111 %
1$
#29940600
0$
#29982300
b101101000 %
1$
#30024000
0$
#30065700
b101101001 %
1$
#30107400
0$
#30149100
b101101010 %
1$
#30190800
0$
#30232500
b101101011 %
1$
#30274200
0$
#30315900
b101101100 %
1$
#30357600
0$
#30399300
b101101101 %
1$
#30441000
0$
#30482700
b101101110 %
1$
#30524400
0$
#30566100
b101101111 %
1$
#30607800
0$
#30649500
b101110000 %
1$
#30691200
0$
#30732900
b101110001 %
1$
#30774600
0$
#30816300
b101110010 %
1$
#30858000
0$
#30899700
b101110011 %
1$
#30941400
0$
#30983100
b101110100 %
1$
#31024800
0$
#31066500
b101110101 %
1$
#31108200
0$
#31149900
b101110110 %
1$
#31191600
0$
#31233300
b101110111 %
1$
#31275000
0$
#31316700
b101111000 %
1$
#31358400
0$
#31400100
b101111001 %
1$
#31441800
0$
#31483500
b101111010 %
1$
#31525200
0$
#31566900
b101111011 %
1$
#31608600
0$
#31650300
b101111100 %
1$
#31692000
0$
#31733700
b101111101 %
1$
#31775400
0$
#31817100
b101111110 %
1$
#31858800
0$
#31900500
b101111111 %
1$
#31942200
0$
#31983900
b110000000 %
1$
#32025600
0$
#32067300
b110000001 %
1$
#32109000
0$
#32150700
b110000010 %
1$
#32192400
0$
#32234100
b110000011 %
1$
#32275800
0$
#32317500
b110000100 %
1$
#32359200
0$
#32400900
b110000101 %
1$
#32442600
0$
#32484300
b110000110 %
1$
#32526000
0$
#32567700
b110000111 %
1$
#32609400
0$
#32651100
b110001000 %
1$
#32692800
0$
#32734500
b110001001 %
1$
#32776200
0$
#32817900
b110001010 %
1$
#32859600
0$
#32901300
b110001011 %
1$
#32943000
0$
#32984700
b110001100 %
1$
#33026400
0$
#33068100
b110001101 %
1$
#33109800
0$
#33151500
b110001110 %
1$
#33193200
0$
#33234900
b110001111 %
1$
#33276600
0$
#33318300
b110010000 %
1$
#33360000
0$
#33401700
b110010001 %
1$
#33443400
0$
#33485100
b110010010 %
1$
#33526800
0$
#33568500
b110010011 %
1$
#33610200
0$
#33651900
b110010100 %
1$
#33693600
0$
#33735300
b110010101 %
1$
#33777000
0$
#33818700
b110010110 %
1$
#33860400
0$
#33902100
b110010111 %
1$
#33943800
0$
#33985500
b110011000 %
1$
#34027200
0$
#34068900
b110011001 %
1$
#34110600
0$
#34152300
b110011010 %
1$
#34194000
0$
#34235700
b110011011 %
1$
#34277400
0$
#34319100
b110011100 %
1$
#34360800
0$
#34402500
b110011101 %
1$
#34444200
0$
#34485900
b110011110 %
1$
#34527600
0$
#34569300
b110011111 %
1$
#34611000
0$
#34652700
b110100000 %
1$
#34694400
0$
#34736100
b110100001 %
1$
#34777800
0$
#34819500
b110100010 %
1$
#34861200
0$
#34902900
b110100011 %
1$
#34944600
0$
#34986300
b110100100 %
1$
#35028000
0$
#35069700
b110100101 %
1$
#35111400
0$
#35153100
b110100110 %
1$
#35194800
0$
#35236500
b110100111 %
1$
#35278200
0$
#35319900
b110101000 %
1$
#35361600
0$
#35403300
b110101001 %
1$
#35445000
0$
#35486700
b110101010 %
1$
#35528400
0$
#35570100
b110101011 %
1$
#35611800
0$
#35653500
b110101100 %
1$
#35695200
0$
#35736900
b110101101 %
1$
#35778600
0$
#35820300
b110101110 %
1$
#35862000
0$
#35903700
b110101111 %
1$
#35945400
0$
#35987100
b110110000 %
1$
#36028800
0$
#36070500
b110110001 %
1$
#36112200
0$
#36153900
b110110010 %
1$
#36195600
0$
#36237300
b110110011 %
1$
#36279000
0$
#36320700
b110110100 %
1$
#36362400
0$
#36404100
b110110101 %
1$
#36445800
0$
#36487500
b110110110 %
1$
#36529200
0$
#36570900
b110110111 %
1$
#36612600
0$
#36654300
b110111000 %
1$
#36696000
0$
#36737700
b110111001 %
1$
#36779400
0$
#36821100
b110111010 %
1$
#36862800
0$
#36904500
b110111011 %
1$
#36946200
0$
#36987900
b110111100 %
1$
#37029600
0$
#37071300
b110111101 %
1$
#37113000
0$
#37154700
b110111110 %
1$
#37196400
0$
#37238100
b110111111 %
1$
#37279800
0$
#37321500
b111000000 %
1$
#37363200
0$
#37404900
b111000001 %
1$
#37446600
0$
#37488300
b111000010 %
1$
#37530000
0$
#37571700
b111000011 %
1$
#37613400
0$
#37655100
b111000100 %
1$
#37696800
0$
#37738500
b111000101 %
1$
#37780200
0$
#37821900
b111000110 %
1$
#37863600
0$
#37905300
b111000111 %
1$
#37947000
0$
#37988700
b111001000 %
1$
#38030400
0$
#38072100
b111001001 %
1$
#38113800
0$
#38155500
b111001010 %
1$
#38197200
0$
#38238900
b111001011 %
1$
#38280600
0$
#38322300
b111001100 %
1$
#38364000
0$
#38405700
b111001101 %
1$
#38447400
0$
#38489100
b111001110 %
1$
#38530800
0$
#38572500
b111001111 %
1$
#38614200
0$
#38655900
b111010000 %
1$
#38697600
0$
#38739300
b111010001 %
1$
#38781000
0$
#38822700
b111010010 %
1$
#38864400
0$
#38906100
b111010011 %
1$
#38947800
0$
#38989500
b111010100 %
1$
#39031200
0$
#39072900
b111010101 %
1$
#39114600
0$
#39156300
b111010110 %
1$
#39198000
0$
#39239700
b111010111 %
1$
#39281400
0$
#39323100
b111011000 %
1$
#39364800
0$
#39406500
b111011001 %
1$
#39448200
0$
#39489900
b111011010 %
1$
#39531600
0$
#39573300
b111011011 %
1$
#39615000
0$
#39656700
b111011100 %
1$
#39698400
0$
#39740100
b111011101 %
1$
#39781800
0$
#39823500
b111011110 %
1$
#39865200
0$
#39906900
b111011111 %
1$
#39948600
0$
#39990300
b111100000 %
1$
#40032000
0$
#40073700
b111100001 %
1$
#40115400
0$
#40157100
b111100010 %
1$
#40198800
0$
#40240500
b111100011 %
1$
#40282200
0$
#40323900
b111100100 %
1$
#40365600
0$
#40407300
b111100101 %
1$
#40449000
0$
#40490700
b111100110 %
1$
#40532400
0$
#40574100
b111100111 %
1$
#40615800
0$
#40657500
b111101000 %
1$
#40699200
0$
#40740900
b111101001 %
1$
#40782600
0$
#40824300
b111101010 %
1$
#40866000
0$
#40907700
b111101011 %
1$
#40949400
0$
#40991100
b111101100 %
1$
#41032800
0$
#41074500
b111101101 %
1$
#41116200
0$
#41157900
b111101110 %
1$
#41199600
0$
#41241300
b111101111 %
1$
#41283000
0$
#41324700
b111110000 %
1$
#41366400
0$
#41408100
b111110001 %
1$
#41449800
0$
#41491500
b111110010 %
1$
#41533200
0$
#41574900
b111110011 %
1$
#41616600
0$
#41658300
b111110100 %
1$
#41700000
0$
#41741700
b111110101 %
1$
#41783400
0$
#41825100
b111110110 %
1$
#41866800
0$
#41908500
b111110111 %
1$
#41950200
0$
#41991900
b111111000 %
1$
#42033600
0$
#42075300
b111111001 %
1$
#42117000
0$
#42158700
b111111010 %
1$
#42200400
0$
#42242100
b111111011 %
1$
#42283800
0$
#42325500
b111111100 %
1$
#42367200
0$
#42408900
b111111101 %
1$
#42450600
0$
#42492300
b111111110 %
1$
#42534000
0$
#42575700
b111111111 %
1$
#42617400
0$
#42659100
b1000000000 %
1$
#42700800
0$
#42742500
b1000000001 %
1$
#42784200
0$
#42825900
b1000000010 %
1$
#42867600
0$
#42909300
b1000000011 %
1$
#42951000
0$
#42992700
b1000000100 %
1$
#43034400
0$
#43076100
b1000000101 %
1$
#43117800
0$
#43159500
b1000000110 %
1$
#43201200
0$
#43242900
b1000000111 %
1$
#43284600
0$
#43326300
b1000001000 %
1$
#43368000
0$
#43409700
b1000001001 %
1$
#43451400
0$
#43493100
b1000001010 %
1$
#43534800
0$
#43576500
b1000001011 %
1$
#43618200
0$
#43659900
b1000001100 %
1$
#43701600
0$
#43743300
b1000001101 %
1$
#43785000
0$
#43826700
b1000001110 %
1$
#43868400
0$
#43910100
b1000001111 %
1$
#43951800
0$
#43993500
b1000010000 %
1$
#44035200
0$
#44076900
b1000010001 %
1$
#44118600
0$
#44160300
b1000010010 %
1$
#44202000
0$
#44243700
b1000010011 %
1$
#44285400
0$
#44327100
b1000010100 %
1$
#44368800
0$
#44410500
b1000010101 %
1$
#44452200
0$
#44493900
b1000010110 %
1$
#44535600
0$
#44577300
b1000010111 %
1$
#44619000
0$
#44660700
b1000011000 %
1$
#44702400
0$
#44744100
b1000011001 %
1$
#44785800
0$
#44827500
b1000011010 %
1$
#44869200
0$
#44910900
b1000011011 %
1$
#44952600
0$
#44994300
b1000011100 %
1$
#45036000
0$
#45077700
b1000011101 %
1$
#45119400
0$
#45161100
b1000011110 %
1$
#45202800
0$
#45244500
b1000011111 %
1$
#45286200
0$
#45327900
b1000100000 %
1$
#45369600
0$
#45411300
b1000100001 %
1$
#45453000
0$
#45494700
b1000100010 %
1$
#45536400
0$
#45578100
b1000100011 %
1$
#45619800
0$
#45661500
b1000100100 %
1$
#45703200
0$
#45744900
b1000100101 %
1$
#45786600
0$
#45828300
b1000100110 %
1$
#45870000
0$
#45911700
b1000100111 %
1$
#45953400
0$
#45995100
b1000101000 %
1$
#46036800
0$
#46078500
b1000101001 %
1$
#46120200
0$
#46161900
b1000101010 %
1$
#46203600
0$
#46245300
b1000101011 %
1$
#46287000
0$
#46328700
b1000101100 %
1$
#46370400
0$
#46412100
b1000101101 %
1$
#46453800
0$
#46495500
b1000101110 %
1$
#46537200
0$
#46578900
b1000101111 %
1$
#46620600
0$
#46662300
b1000110000 %
1$
#46704000
0$
#46745700
b1000110001 %
1$
#46787400
0$
#46829100
b1000110010 %
1$
#46870800
0$
#46912500
b1000110011 %
1$
#46954200
0$
#46995900
b1000110100 %
1$
#47037600
0$
#47079300
b1000110101 %
1$
#47121000
0$
#47162700
b1000110110 %
1$
#47204400
0$
#47246100
b1000110111 %
1$
#47287800
0$
#47329500
b1000111000 %
1$
#47371200
0$
#47412900
b1000111001 %
1$
#47454600
0$
#47496300
b1000111010 %
1$
#47538000
0$
#47579700
b1000111011 %
1$
#47621400
0$
#47663100
b1000111100 %
1$
#47704800
0$
#47746500
b1000111101 %
1$
#47788200
0$
#47829900
b1000111110 %
1$
#47871600
0$
#47913300
b1000111111 %
1$
#47955000
0$
#47996700
b1001000000 %
1$
#48038400
0$
#48080100
b1001000001 %
1$
#48121800
0$
#48163500
b1001000010 %
1$
#48205200
0$
#48246900
b1001000011 %
1$
#48288600
0$
#48330300
b1001000100 %
1$
#48372000
0$
#48413700
b1001000101 %
1$
#48455400
0$
#48497100
b1001000110 %
1$
#48538800
0$
#48580500
b1001000111 %
1$
#48622200
0$
#48663900
b1001001000 %
1$
#48705600
0$
#48747300
b1001001001 %
1$
#48789000
0$
#48830700
b1001001010 %
1$
#48872400
0$
#48914100
b1001001011 %
1$
#48955800
0$
#48997500
b1001001100 %
1$
#49039200
0$
#49080900
b1001001101 %
1$
#49122600
0$
#49164300
b1001001110 %
1$
#49206000
0$
#49247700
b1001001111 %
1$
#49289400
0$
#49331100
b1001010000 %
1$
#49372800
0$
#49414500
b1001010001 %
1$
#49456200
0$
#49497900
b1001010010 %
1$
#49539600
0$
#49581300
b1001010011 %
1$
#49623000
0$
#49664700
b1001010100 %
1$
#49706400
0$
#49748100
b1001010101 %
1$
#49789800
0$
#49831500
b1001010110 %
1$
#49873200
0$
#49914900
b1001010111 %
1$
#49956600
0$
#49998300
b1001011000 %
1$
#50040000
0$
#50081700
b1001011001 %
1$
#50123400
0$
#50165100
b1001011010 %
1$
#50206800
0$
#50248500
b1001011011 %
1$
#50290200
0$
#50331900
b1001011100 %
1$
#50373600
0$
#50415300
b1001011101 %
1$
#50457000
0$
#50498700
b1001011110 %
1$
#50540400
0$
#50582100
b1001011111 %
1$
#50623800
0$
#50665500
b1001100000 %
1$
#50707200
0$
#50748900
b1001100001 %
1$
#50790600
0$
#50832300
b1001100010 %
1$
#50874000
0$
#50915700
b1001100011 %
1$
#50957400
0$
#50999100
b1001100100 %
1$
#51040800
0$
#51082500
b1001100101 %
1$
#51124200
0$
#51165900
b1001100110 %
1$
#51207600
0$
#51249300
b1001100111 %
1$
#51291000
0$
#51332700
b1001101000 %
1$
#51374400
0$
#51416100
b1001101001 %
1$
#51457800
0$
#51499500
b1001101010 %
1$
#51541200
0$
#51582900
b1001101011 %
1$
#51624600
0$
#51666300
b1001101100 %
1$
#51708000
0$
#51749700
b1001101101 %
1$
#51791400
0$
