g5/xDFF/D/DFF.v
module DFF (
    input wire clk,
    input wire D,
    output reg Q
);


always @(negedge clk)  begin
    /* case (D)
        1'b0 : Q <=1'b0; 
        1'b1 : Q <=1'b1; 
    endcase; */
    Q <= D;


end
endmodule

g5/LIFO_8_4/SSBR_4_bits/SSBR_4_bits.v
`include "D/DFF.v"

module SSBR_4_bits (
    input wire clk,
    input wire D,
    input wire dir,
    output wire QL,
    output wire QR
);

wire tmp_q0;
wire tmp_q1;
wire tmp_q2;
wire tmp_q3;


wire mux_out0;
wire mux_out1;
wire mux_out2;
wire mux_out3;

// D flip-flops
DFF DFF_0 (.clk(clk), .D(mux_out0), .Q(tmp_q0));
DFF DFF_1 (.clk(clk), .D(mux_out1), .Q(tmp_q1));
DFF DFF_2 (.clk(clk), .D(mux_out2), .Q(tmp_q2));
DFF DFF_3 (.clk(clk), .D(mux_out3), .Q(tmp_q3));

// Multiplexers to select data based on shift direction
assign mux_out0 = (dir == 1'b0) ? tmp_q1 : D;
assign mux_out1 = (dir == 1'b0) ? tmp_q2 : tmp_q0;
assign mux_out2 = (dir == 1'b0) ? tmp_q3 : tmp_q1;
assign mux_out3 = (dir == 1'b0) ? D: tmp_q2;

assign QL = (dir == 1'b0) ? tmp_q1 : 1'b1;
assign QR = (dir == 1'b0) ?  1'b1 : tmp_q3;

endmodule

g5/SSBR_4_bits/SSBR_4_bits_tb.v

`default_nettype none
`timescale 100 ns / 10 ns

module SSBR_4_bits_tb();

parameter DURATION = 10;
reg clk0 = 0;
always #0.5 clk0 = ~clk0;

reg  d0, dir;
wire qr, ql;

SSBR_4_bits UUT (.clk(clk0), .D(d0), .dir(dir), .QR(qr), .QL(ql));
integer i;
reg [3:0] i_b;

initial begin
  // Directly specify the VCD file name without using macros
  $dumpfile("SSBR_4_bits_tb.vcd");
  // Dump variables for the jk_tb module
  $dumpvars(0, SSBR_4_bits_tb);
  i_b = 4'b0100;
  dir = 1;
  for (i = 0;i<4 ; i = i+1) begin
    d0 = i_b[i];
    #1;
  end
  dir = 0;
  for (i = 0;i<4 ; i = i+1) begin
    d0 = i_b[i];
    #1;
  end
   dir = 1;
    
  #(DURATION) $display("End of simulation");
  $finish;
end

endmodule

g5/SSBR_4_bits/SSBR_4_bits_tb.vcd
$date
	Wed May 29 10:52:40 2024
$end
$version
	Icarus Verilog
$end
$timescale
	1ps
$end
$scope module SSBR_4_bits_tb $end
$var wire 1 ! qr $end
$var wire 1 " ql $end
$var parameter 32 # DURATION $end
$var reg 1 $ clk0 $end
$var reg 1 % d0 $end
$var reg 1 & dir $end
$var reg 4 ' i_b [3:0] $end
$var integer 32 ( i [31:0] $end
$scope module UUT $end
$var wire 1 % D $end
$var wire 1 $ clk $end
$var wire 1 & dir $end
$var wire 1 ) tmp_q3 $end
$var wire 1 * tmp_q2 $end
$var wire 1 + tmp_q1 $end
$var wire 1 , tmp_q0 $end
$var wire 1 - mux_out3 $end
$var wire 1 . mux_out2 $end
$var wire 1 / mux_out1 $end
$var wire 1 0 mux_out0 $end
$var wire 1 ! QR $end
$var wire 1 " QL $end
$scope module DFF_0 $end
$var wire 1 0 D $end
$var wire 1 $ clk $end
$var reg 1 , Q $end
$upscope $end
$scope module DFF_1 $end
$var wire 1 / D $end
$var wire 1 $ clk $end
$var reg 1 + Q $end
$upscope $end
$scope module DFF_2 $end
$var wire 1 . D $end
$var wire 1 $ clk $end
$var reg 1 * Q $end
$upscope $end
$scope module DFF_3 $end
$var wire 1 - D $end
$var wire 1 $ clk $end
$var reg 1 ) Q $end
$upscope $end
$upscope $end
$upscope $end
$enddefinitions $end
$comment Show the parameter values. $end
$dumpall
b1010 #
$end
#0
$dumpvars
00
x/
x.
x-
x,
x+
x*
x)
b0 (
b100 '
1&
0%
0$
1"
x!
$end
#50000
1$
#100000
0/
0,
0$
b1 (
#150000
1$
#200000
1/
0.
1,
0+
10
0$
1%
b10 (
#250000
1$
#300000
0-
1.
0/
0*
1+
0,
00
0$
0%
b11 (
#350000
1$
#400000
0"
1/
0+
1*
0)
00
0.
1!
0$
0&
b0 (
#450000
1$
#500000
0/
1"
10
0*
1+
0$
b1 (
#550000
1$
#600000
0"
00
1.
1,
0+
1)
1-
0$
1%
b10 (
#650000
1$
#700000
0.
1/
0)
1*
0,
0-
0$
0%
b11 (
#750000
1$
#800000
1.
1+
0*
0/
0-
1"
0!
0$
1&
b100 (
#850000
1$
#900000
1-
0.
1*
0+
0$
#950000
1$
#1000000
0-
1!
0*
1)
0$
#1050000
1$
#1100000
0!
0)
0$
