g2/ten/ten.v

module ten (
    input wire [4:0] A,
    output wire P
);

integer decimal;
integer s;
integer i;

assign P = s;

always @* begin   
decimal = A[4]*16 + A[3]*8 + A[2]*4 + A[1]*2 + A[0]*1;
s = 1;
for (i = 2; i<decimal; i = i + 1 ) 
    begin
        if ((decimal % i == 0) && s == 1)
        begin
            s = 0;
        end
    end
end
    
endmodule

g2/ten/ten_tb.v
`default_nettype none
`define DUMPSTR(x) `"ten_tb.vcd`"
`timescale 100 ns / 10 ns

module ten_tb();

parameter DURATION = 10;
reg clk = 0;
always #0.5 clk = ~clk;

reg [4:0] A0;

wire p0;

ten UUT (
           .A(A0),
           .P(p0)
         );

integer i;

initial begin

  $dumpfile(`DUMPSTR(`VCD_OUTPUT));
  $dumpvars(0, ten_tb);

  for (i = 0;i<32 ; i = i+1 ) 
  begin
      $display ("Current loop # %0d", i);
      $display ("Current loop # %0b", i);
      #1
      A0 = i;
  end

   #(DURATION) $display("End of simulation");
  $finish;
end

endmodule

g2/ten/ten_tb.vcd
$date
	Wed Apr 24 16:39:41 2024
$end
$version
	Icarus Verilog
$end
$timescale
	1ps
$end
$scope module ten_tb $end
$var wire 1 ! p0 $end
$var parameter 32 " DURATION $end
$var reg 5 # A0 [4:0] $end
$var reg 1 $ clk $end
$var integer 32 % i [31:0] $end
$scope module UUT $end
$var wire 5 & A [4:0] $end
$var wire 1 ! P $end
$var integer 32 ' decimal [31:0] $end
$var integer 32 ( i [31:0] $end
$var integer 32 ) s [31:0] $end
$upscope $end
$upscope $end
$enddefinitions $end
$comment Show the parameter values. $end
$dumpall
b1010 "
$end
#0
$dumpvars
bx )
bx (
bx '
bx &
b0 %
0$
bx #
x!
$end
#50000
1$
#100000
1!
b10 (
b1 )
b0 '
0$
b1 %
b0 #
b0 &
#150000
1$
#200000
b1 '
0$
b10 %
b1 #
b1 &
#250000
1$
#300000
b10 '
0$
b11 %
b10 #
b10 &
#350000
1$
#400000
b11 (
b11 '
0$
b100 %
b11 #
b11 &
#450000
1$
#500000
0!
b0 )
b100 (
b100 '
0$
b101 %
b100 #
b100 &
#550000
1$
#600000
1!
b101 (
b1 )
b101 '
0$
b110 %
b101 #
b101 &
#650000
1$
#700000
0!
b0 )
b110 (
b110 '
0$
b111 %
b110 #
b110 &
#750000
1$
#800000
1!
b111 (
b1 )
b111 '
0$
b1000 %
b111 #
b111 &
#850000
1$
#900000
0!
b0 )
b1000 (
b1000 '
0$
b1001 %
b1000 #
b1000 &
#950000
1$
#1000000
b1001 (
b0 )
b1001 '
0$
b1010 %
b1001 #
b1001 &
#1050000
1$
#1100000
b1010 (
b0 )
b1010 '
0$
b1011 %
b1010 #
b1010 &
#1150000
1$
#1200000
1!
b1011 (
b1 )
b1011 '
0$
b1100 %
b1011 #
b1011 &
#1250000
1$
#1300000
0!
b0 )
b1100 (
b1100 '
0$
b1101 %
b1100 #
b1100 &
#1350000
1$
#1400000
1!
b1101 (
b1 )
b1101 '
0$
b1110 %
b1101 #
b1101 &
#1450000
1$
#1500000
0!
b0 )
b1110 (
b1110 '
0$
b1111 %
b1110 #
b1110 &
#1550000
1$
#1600000
b1111 (
b0 )
b1111 '
0$
b10000 %
b1111 #
b1111 &
#1650000
1$
#1700000
b10000 (
b0 )
b10000 '
0$
b10001 %
b10000 #
b10000 &
#1750000
1$
#1800000
1!
b10001 (
b1 )
b10001 '
0$
b10010 %
b10001 #
b10001 &
#1850000
1$
#1900000
0!
b0 )
b10010 (
b10010 '
0$
b10011 %
b10010 #
b10010 &
#1950000
1$
#2000000
1!
b10011 (
b1 )
b10011 '
0$
b10100 %
b10011 #
b10011 &
#2050000
1$
#2100000
0!
b0 )
b10100 (
b10100 '
0$
b10101 %
b10100 #
b10100 &
#2150000
1$
#2200000
b10101 (
b0 )
b10101 '
0$
b10110 %
b10101 #
b10101 &
#2250000
1$
#2300000
b10110 (
b0 )
b10110 '
0$
b10111 %
b10110 #
b10110 &
#2350000
1$
#2400000
1!
b10111 (
b1 )
b10111 '
0$
b11000 %
b10111 #
b10111 &
#2450000
1$
#2500000
0!
b0 )
b11000 (
b11000 '
0$
b11001 %
b11000 #
b11000 &
#2550000
1$
#2600000
b11001 (
b0 )
b11001 '
0$
b11010 %
b11001 #
b11001 &
#2650000
1$
#2700000
b11010 (
b0 )
b11010 '
0$
b11011 %
b11010 #
b11010 &
#2750000
1$
#2800000
b11011 (
b0 )
b11011 '
0$
b11100 %
b11011 #
b11011 &
#2850000
1$
#2900000
b11100 (
b0 )
b11100 '
0$
b11101 %
b11100 #
b11100 &
#2950000
1$
#3000000
1!
b11101 (
b1 )
b11101 '
0$
b11110 %
b11101 #
b11101 &
#3050000
1$
#3100000
0!
b0 )
b11110 (
b11110 '
0$
b11111 %
b11110 #
b11110 &
#3150000
1$
#3200000
1!
b11111 (
b1 )
b11111 '
0$
b100000 %
b11111 #
b11111 &
